{"autoLightData":{"isAutoLightEnabled":false,"timeProgress":0.5,"minutesInDay":10},"saveObjectContainers":[{"saveObjects":{"objectId":248,"instanceId":-55784,"modedObjectId":"","localId":0,"parentId":-1,"position":{"x":0.0,"y":0.0,"z":0.0},"rotation":{"x":0.0,"y":0.0,"z":0.0289526787},"scale":{"x":1.0,"y":1.0,"z":1.0},"color":{"r":0.0,"g":0.0,"b":0.0,"a":0.0},"intensity":0.0,"layer":0,"sortingLayer":"Default","orderLayer":0,"gravity":true,"freezed":false,"rotationFrozen":false,"notBreakable":false,"isMeltable":false,"isHuman":false,"isActivationForced":false,"TreeBranch":null,"LightSaveData":{"IsActive":false,"ColorIsChanged":true,"Color":{"r":0.0,"g":0.0,"b":0.0,"a":0.0},"IsBrokenByWater":false,"ChildrenSaveData":null,"<IsActive>k__BackingField":false,"<ColorIsChanged>k__BackingField":true,"<Color>k__BackingField":{"r":0.0,"g":0.0,"b":0.0,"a":0.0},"<IsBrokenByWater>k__BackingField":false,"<ChildrenSaveData>k__BackingField":null},"BreakableSaveData":null,"humanData":[],"mechanicData":[{"activationInput":0.0,"floatParameters":[0.0],"mechanicSerializedInputs":"[{\"Key\":\"activation\",\"DataType\":2,\"DataName\":\"activation\",\"CanBeEdit\":false,\"GateData\":\"{\\\"Value\\\":0.0,\\\"Default\\\":0.0,\\\"Min\\\":-3.40282347E+38,\\\"Max\\\":3.40282347E+38,\\\"IsCheckbox\\\":false}\"}]"}],"brokenJoints":[],"hingeJoints":[],"distJoints":[],"constraints":[],"collisionIgnores":[],"addData":[],"saveMetaDatas":[{"key":"chip_tps","boolValue":false,"stringValue":null,"intValue":240,"floatValue":0.0,"vector2Value":{"x":0.0,"y":0.0},"vector3Value":{"x":0.0,"y":0.0,"z":0.0},"vector4Value":{"x":0.0,"y":0.0,"z":0.0,"w":0.0,"magnitude":0.0,"sqrMagnitude":0.0}},{"key":"chip_period_name_index","boolValue":false,"stringValue":null,"intValue":2,"floatValue":0.0,"vector2Value":{"x":0.0,"y":0.0},"vector3Value":{"x":0.0,"y":0.0,"z":0.0},"vector4Value":{"x":0.0,"y":0.0,"z":0.0,"w":0.0,"magnitude":0.0,"sqrMagnitude":0.0}},{"key":"chip_inputs","boolValue":false,"stringValue":"[\n  {\n    \"Key\": \"activation\",\n    \"DataName\": \"activation\",\n    \"SerializedValue\": \"{\\\"Value\\\":0.0,\\\"Default\\\":0.0,\\\"Min\\\":-3.40282347E+38,\\\"Max\\\":3.40282347E+38,\\\"IsCheckbox\\\":false}\",\n    \"GateDataType\": 2\n  },\n  {\n    \"Key\": \"object_8b65\",\n    \"DataName\": \"#Object\",\n    \"SerializedValue\": null,\n    \"GateDataType\": 1\n  },\n  {\n    \"Key\": \"targetposition_7738\",\n    \"DataName\": \"#TargetPosition\",\n    \"SerializedValue\": \"{\\\"Value\\\": {\\\"x\\\": 0.0, \\\"y\\\": 0.0, \\\"z\\\": 0.0, \\\"w\\\": 0.0, \\\"magnitude\\\": 0.0, \\\"sqrMagnitude\\\": 0.0}, \\\"Default\\\": {\\\"x\\\": 0.0, \\\"y\\\": 0.0, \\\"z\\\": 0.0, \\\"w\\\": 0.0, \\\"magnitude\\\": 0.0, \\\"sqrMagnitude\\\": 0.0}}\",\n    \"GateDataType\": 8\n  },\n  {\n    \"Key\": \"kp_9d46\",\n    \"DataName\": \"#Kp\",\n    \"SerializedValue\": \"{\\\"Value\\\": 0.0, \\\"Default\\\": 0.0, \\\"Min\\\": -3.40282347e+38, \\\"Max\\\": 3.40282347e+38, \\\"IsCheckbox\\\": false}\",\n    \"GateDataType\": 2\n  },\n  {\n    \"Key\": \"ki_3103\",\n    \"DataName\": \"#Ki\",\n    \"SerializedValue\": \"{\\\"Value\\\": 0.0, \\\"Default\\\": 0.0, \\\"Min\\\": -3.40282347e+38, \\\"Max\\\": 3.40282347e+38, \\\"IsCheckbox\\\": false}\",\n    \"GateDataType\": 2\n  },\n  {\n    \"Key\": \"kd_4c22\",\n    \"DataName\": \"#Kd\",\n    \"SerializedValue\": \"{\\\"Value\\\": 0.0, \\\"Default\\\": 0.0, \\\"Min\\\": -3.40282347e+38, \\\"Max\\\": 3.40282347e+38, \\\"IsCheckbox\\\": false}\",\n    \"GateDataType\": 2\n  },\n  {\n    \"Key\": \"brakedistance_4ce2\",\n    \"DataName\": \"#BrakeDistance\",\n    \"SerializedValue\": \"{\\\"Value\\\": 0.0, \\\"Default\\\": 0.0, \\\"Min\\\": -3.40282347e+38, \\\"Max\\\": 3.40282347e+38, \\\"IsCheckbox\\\": false}\",\n    \"GateDataType\": 2\n  },\n  {\n    \"Key\": \"brakeaggression_107f\",\n    \"DataName\": \"#BrakeAggression\",\n    \"SerializedValue\": \"{\\\"Value\\\": 0.0, \\\"Default\\\": 0.0, \\\"Min\\\": -3.40282347e+38, \\\"Max\\\": 3.40282347e+38, \\\"IsCheckbox\\\": false}\",\n    \"GateDataType\": 2\n  },\n  {\n    \"Key\": \"gravity_ba64\",\n    \"DataName\": \"#Gravity\",\n    \"SerializedValue\": \"{\\\"Value\\\": 0.0, \\\"Default\\\": 0.0, \\\"Min\\\": -3.40282347e+38, \\\"Max\\\": 3.40282347e+38, \\\"IsCheckbox\\\": false}\",\n    \"GateDataType\": 2\n  },\n  {\n    \"Key\": \"resetintegral_55f7\",\n    \"DataName\": \"#ResetIntegral\",\n    \"SerializedValue\": \"{\\\"Value\\\": 0.0, \\\"Default\\\": 0.0, \\\"Min\\\": -3.40282347e+38, \\\"Max\\\": 3.40282347e+38, \\\"IsCheckbox\\\": false}\",\n    \"GateDataType\": 2\n  }\n]","intValue":0,"floatValue":0.0,"vector2Value":{"x":0.0,"y":0.0},"vector3Value":{"x":0.0,"y":0.0,"z":0.0},"vector4Value":{"x":0.0,"y":0.0,"z":0.0,"w":0.0,"magnitude":0.0,"sqrMagnitude":0.0}},{"key":"chip_outputs","boolValue":false,"stringValue":"[\n  {\n    \"Key\": \"entity\",\n    \"DataName\": \"entity\",\n    \"SerializedValue\": null,\n    \"GateDataType\": 1\n  },\n  {\n    \"Key\": \"activation\",\n    \"DataName\": \"activation\",\n    \"SerializedValue\": \"{\\\"Value\\\":0.0,\\\"Default\\\":0.0,\\\"Min\\\":-3.40282347E+38,\\\"Max\\\":3.40282347E+38,\\\"IsCheckbox\\\":false}\",\n    \"GateDataType\": 2\n  },\n  {\n    \"Key\": \"force_8af7\",\n    \"DataName\": \"#Force\",\n    \"SerializedValue\": \"{\\\"Value\\\": {\\\"x\\\": 0.0, \\\"y\\\": 0.0, \\\"z\\\": 0.0, \\\"w\\\": 0.0, \\\"magnitude\\\": 0.0, \\\"sqrMagnitude\\\": 0.0}, \\\"Default\\\": {\\\"x\\\": 0.0, \\\"y\\\": 0.0, \\\"z\\\": 0.0, \\\"w\\\": 0.0, \\\"magnitude\\\": 0.0, \\\"sqrMagnitude\\\": 0.0}}\",\n    \"GateDataType\": 8\n  },\n  {\n    \"Key\": \"debugisbraking_ddd9\",\n    \"DataName\": \"#DebugIsBraking\",\n    \"SerializedValue\": \"{\\\"Value\\\": 0.0, \\\"Default\\\": 0.0, \\\"Min\\\": -3.40282347e+38, \\\"Max\\\": 3.40282347e+38, \\\"IsCheckbox\\\": false}\",\n    \"GateDataType\": 2\n  },\n  {\n    \"Key\": \"debugmaxspeed_9de3\",\n    \"DataName\": \"#DebugMaxSpeed\",\n    \"SerializedValue\": \"{\\\"Value\\\": 0.0, \\\"Default\\\": 0.0, \\\"Min\\\": -3.40282347e+38, \\\"Max\\\": 3.40282347e+38, \\\"IsCheckbox\\\": false}\",\n    \"GateDataType\": 2\n  },\n  {\n    \"Key\": \"debugbrakeforce_28b7\",\n    \"DataName\": \"#DebugBrakeForce\",\n    \"SerializedValue\": \"{\\\"Value\\\": 0.0, \\\"Default\\\": 0.0, \\\"Min\\\": -3.40282347e+38, \\\"Max\\\": 3.40282347e+38, \\\"IsCheckbox\\\": false}\",\n    \"GateDataType\": 2\n  }\n]","intValue":0,"floatValue":0.0,"vector2Value":{"x":0.0,"y":0.0},"vector3Value":{"x":0.0,"y":0.0,"z":0.0},"vector4Value":{"x":0.0,"y":0.0,"z":0.0,"w":0.0,"magnitude":0.0,"sqrMagnitude":0.0}},{"key":"chip_variables","boolValue":false,"stringValue":"[]","intValue":0,"floatValue":0.0,"vector2Value":{"x":0.0,"y":0.0},"vector3Value":{"x":0.0,"y":0.0,"z":0.0},"vector4Value":{"x":0.0,"y":0.0,"z":0.0,"w":0.0,"magnitude":0.0,"sqrMagnitude":0.0}},{"key":"chip_graph","boolValue":false,"stringValue":"{\"ValidationState\":1,\"Nodes\":[{\"Id\":\"AddNumbersNodeViewModel : 538519d9-4437-4b43-b130-9495d0a12acc\",\"ModelVersion\":1,\"Version\":\"0.1\",\"OperationType\":2304,\"Inputs\":[{\"Id\":\"AddNumbersNodeViewModel : 538519d9-4437-4b43-b130-9495d0a12acc\\nInput : Number 962dc162-85c8-4f64-a8fe-421a0b584cb9\",\"DataType\":2,\"connectedOutputIdModel\":{\"Id\":\"ConstantNodeViewModel : 62b4a7e4-7ed7-4882-9b30-a612cc39bba0\\nOutput : Number cd872a86-5d43-43f5-8454-c052b928d885\",\"NodeId\":\"ConstantNodeViewModel : 62b4a7e4-7ed7-4882-9b30-a612cc39bba0\"}},{\"Id\":\"AddNumbersNodeViewModel : 538519d9-4437-4b43-b130-9495d0a12acc\\nInput : Number c5fcc0fd-efe3-4752-9fa4-c3fdf0b944bc\",\"DataType\":2,\"connectedOutputIdModel\":null}],\"Outputs\":[{\"Id\":\"AddNumbersNodeViewModel : 538519d9-4437-4b43-b130-9495d0a12acc\\nOutput : Number 9bb7dac7-1e5f-4163-9c02-5bb0a9585e9f\",\"DataType\":2,\"ConnectedInputsIds\":[{\"Id\":\"IdentityNodeViewModel : bdda07dc-0a55-4139-a59f-88545c55b44a\\nInput : Number 6dead178-e9f7-40a1-b262-2c0bd982535a\",\"NodeId\":\"IdentityNodeViewModel : bdda07dc-0a55-4139-a59f-88545c55b44a\"}]}],\"VisualPosition\":{\"x\":2000.0,\"y\":-1500.0,\"normalized\":{\"x\":-0.5547002,\"y\":0.832050264,\"magnitude\":1.0,\"sqrMagnitude\":1.0},\"magnitude\":216.333084,\"sqrMagnitude\":46800.0},\"VisualCollapsed\":false,\"MechanicConnectionId\":null,\"GateDataType\":2,\"SaveData\":null},{\"Id\":\"ConstantNodeViewModel : 62b4a7e4-7ed7-4882-9b30-a612cc39bba0\",\"ModelVersion\":1,\"Version\":\"0.1\",\"OperationType\":257,\"Inputs\":[],\"Outputs\":[{\"Id\":\"ConstantNodeViewModel : 62b4a7e4-7ed7-4882-9b30-a612cc39bba0\\nOutput : Number cd872a86-5d43-43f5-8454-c052b928d885\",\"DataType\":2,\"ConnectedInputsIds\":[{\"Id\":\"AddNumbersNodeViewModel : 538519d9-4437-4b43-b130-9495d0a12acc\\nInput : Number 962dc162-85c8-4f64-a8fe-421a0b584cb9\",\"NodeId\":\"AddNumbersNodeViewModel : 538519d9-4437-4b43-b130-9495d0a12acc\"}]}],\"VisualPosition\":{\"x\":1200.0,\"y\":300.0,\"normalized\":{\"x\":-0.9881739,\"y\":0.15333733,\"magnitude\":1.0,\"sqrMagnitude\":1.0},\"magnitude\":1173.88245,\"sqrMagnitude\":1378000.0},\"VisualCollapsed\":false,\"MechanicConnectionId\":null,\"GateDataType\":2,\"SaveData\":\"{\\n  \\\"DataValue\\\": \\\"0\\\"\\n}\"},{\"Id\":\"IdentityNodeViewModel : bdda07dc-0a55-4139-a59f-88545c55b44a\",\"ModelVersion\":1,\"Version\":\"0.1\",\"OperationType\":1,\"Inputs\":[{\"Id\":\"IdentityNodeViewModel : bdda07dc-0a55-4139-a59f-88545c55b44a\\nInput : Number 6dead178-e9f7-40a1-b262-2c0bd982535a\",\"DataType\":2,\"connectedOutputIdModel\":{\"Id\":\"AddNumbersNodeViewModel : 538519d9-4437-4b43-b130-9495d0a12acc\\nOutput : Number 9bb7dac7-1e5f-4163-9c02-5bb0a9585e9f\",\"NodeId\":\"AddNumbersNodeViewModel : 538519d9-4437-4b43-b130-9495d0a12acc\"}}],\"Outputs\":[{\"Id\":\"IdentityNodeViewModel : bdda07dc-0a55-4139-a59f-88545c55b44a\\nOutput : Number fd32b0c7-c9db-4136-88fc-2a3894a3fc57\",\"DataType\":2,\"ConnectedInputsIds\":[]}],\"VisualPosition\":{\"x\":2800.0,\"y\":-1500.0,\"normalized\":{\"x\":0.976744354,\"y\":0.2144073,\"magnitude\":1.0,\"sqrMagnitude\":1.0},\"magnitude\":839.5237,\"sqrMagnitude\":704800.0},\"VisualCollapsed\":false,\"MechanicConnectionId\":null,\"GateDataType\":2,\"SaveData\":null},{\"Id\":\"AddNumbersNodeViewModel : d9c8b7a6-f5e4-4d3c-b2a1-09876543210f\",\"ModelVersion\":1,\"Version\":\"0.1\",\"OperationType\":2304,\"Inputs\":[{\"Id\":\"AddNumbersNodeViewModel : d9c8b7a6-f5e4-4d3c-b2a1-09876543210f\\nInput : Number c8b7a6f5-e4d3-4c2b-b1a0-fedcba987654\",\"DataType\":2,\"connectedOutputIdModel\":null},{\"Id\":\"AddNumbersNodeViewModel : d9c8b7a6-f5e4-4d3c-b2a1-09876543210f\\nInput : Number b7a6f5e4-d3c2-4b1a-a09f-edcba9876543\",\"DataType\":2,\"connectedOutputIdModel\":null}],\"Outputs\":[{\"Id\":\"AddNumbersNodeViewModel : d9c8b7a6-f5e4-4d3c-b2a1-09876543210f\\nOutput : Number a6f5e4d3-c2b1-4a09-9f8e-dcba98765432\",\"DataType\":2,\"ConnectedInputsIds\":[]}],\"VisualPosition\":{\"x\":2800.0,\"y\":-900.0,\"normalized\":{\"x\":-0.3011391,\"y\":0.9535372,\"magnitude\":1.0,\"sqrMagnitude\":1.0},\"magnitude\":398.497162,\"sqrMagnitude\":158800.0},\"VisualCollapsed\":false,\"MechanicConnectionId\":null,\"GateDataType\":2,\"SaveData\":null},{\"Id\":\"RootNodeViewModel : 022a6f67-b0b8-4000-8f0c-47a4ddb6b8f5\",\"OperationType\":256,\"Inputs\":[],\"Outputs\":[{\"Id\":\"RootNodeViewModel : 022a6f67-b0b8-4000-8f0c-47a4ddb6b8f5\\nOutput : Number 5f50053a-9988-48c8-ba4d-4192305a6578\",\"DataType\":1,\"ConnectedInputsIds\":[{\"Id\":\"PositionEntityNodeViewModel : bb346c15-8028-4e53-846c-d9bbe55d62e9\\\\nInput : object c4501880-ef4b-4bfe-bd49-99a95ad40d61\",\"NodeId\":\"PositionEntityNodeViewModel : bb346c15-8028-4e53-846c-d9bbe55d62e9\"},{\"Id\":\"VelocityEntityNodeViewModel : 087d34ce-5f0a-4d5d-b0a3-5a03559b323b\\\\nInput : object 5a4c6c30-0b63-4362-938b-9819966d1a82\",\"NodeId\":\"VelocityEntityNodeViewModel : 087d34ce-5f0a-4d5d-b0a3-5a03559b323b\"},{\"Id\":\"MassEntityNodeViewModel : e64f2c05-7909-49f9-ad63-346227051a8f\\\\nInput : object 4773710b-542d-418a-b0f1-c937672ff67d\",\"NodeId\":\"MassEntityNodeViewModel : e64f2c05-7909-49f9-ad63-346227051a8f\"}]}],\"MechanicConnectionId\":\"object_8b65\",\"GateDataType\":1,\"SaveData\":null,\"VisualPosition\":{\"x\":-2800.0,\"y\":-2100.0},\"VisualCollapsed\":false,\"ModelVersion\":1,\"Version\":\"0.1\"},{\"Id\":\"RootNodeViewModel : 1cd4a012-4386-41c1-a1a2-89d3620d5f6f\",\"OperationType\":256,\"Inputs\":[],\"Outputs\":[{\"Id\":\"RootNodeViewModel : 1cd4a012-4386-41c1-a1a2-89d3620d5f6f\\nOutput : Number 26610507-63a6-4560-b882-232bd92c3087\",\"DataType\":8,\"ConnectedInputsIds\":[{\"Id\":\"SplitVectorNodeViewModel : 7553a9ea-0c6a-4ab1-b869-db5b8bb1ce29\\\\nInput : Input b961996c-9743-4b91-89f0-1b35cd1d9f2c\",\"NodeId\":\"SplitVectorNodeViewModel : 7553a9ea-0c6a-4ab1-b869-db5b8bb1ce29\"}]}],\"MechanicConnectionId\":\"targetposition_7738\",\"GateDataType\":8,\"SaveData\":null,\"VisualPosition\":{\"x\":-2000.0,\"y\":900.0},\"VisualCollapsed\":false,\"ModelVersion\":1,\"Version\":\"0.1\"},{\"Id\":\"RootNodeViewModel : 57eea8e8-0905-4271-bd85-8a1841ed9b20\",\"OperationType\":256,\"Inputs\":[],\"Outputs\":[{\"Id\":\"RootNodeViewModel : 57eea8e8-0905-4271-bd85-8a1841ed9b20\\nOutput : Number f857ebc8-1bcc-418a-bf02-13729840f813\",\"DataType\":2,\"ConnectedInputsIds\":[{\"Id\":\"MultiplyNumbersNodeViewModel : aa4e292a-2645-4468-9eb1-5908b7390585\\\\nInput : B 0486808c-bd6b-48f1-a0cf-b013d2a9d96a\",\"NodeId\":\"MultiplyNumbersNodeViewModel : aa4e292a-2645-4468-9eb1-5908b7390585\"}]}],\"MechanicConnectionId\":\"kp_9d46\",\"GateDataType\":2,\"SaveData\":null,\"VisualPosition\":{\"x\":-2800.0,\"y\":-1500.0},\"VisualCollapsed\":false,\"ModelVersion\":1,\"Version\":\"0.1\"},{\"Id\":\"RootNodeViewModel : f82094b8-28ff-464a-8fd5-b91ee6e9887c\",\"OperationType\":256,\"Inputs\":[],\"Outputs\":[{\"Id\":\"RootNodeViewModel : f82094b8-28ff-464a-8fd5-b91ee6e9887c\\nOutput : Number 1d8f6e84-9336-4fef-be29-671962ebe0f1\",\"DataType\":2,\"ConnectedInputsIds\":[{\"Id\":\"MultiplyNumbersNodeViewModel : 18cf38ce-71c6-4cb2-99f3-d8390b4d0ef2\\\\nInput : B e869ab3b-404d-4ec6-9e25-cc0f12301fb7\",\"NodeId\":\"MultiplyNumbersNodeViewModel : 18cf38ce-71c6-4cb2-99f3-d8390b4d0ef2\"}]}],\"MechanicConnectionId\":\"ki_3103\",\"GateDataType\":2,\"SaveData\":null,\"VisualPosition\":{\"x\":-2800.0,\"y\":-300.0},\"VisualCollapsed\":false,\"ModelVersion\":1,\"Version\":\"0.1\"},{\"Id\":\"RootNodeViewModel : 5d74f93c-448b-484b-9f75-6a82da73d521\",\"OperationType\":256,\"Inputs\":[],\"Outputs\":[{\"Id\":\"RootNodeViewModel : 5d74f93c-448b-484b-9f75-6a82da73d521\\nOutput : Number a559cbd6-7fd7-434d-a54c-26beda9f7bcd\",\"DataType\":2,\"ConnectedInputsIds\":[{\"Id\":\"MultiplyNumbersNodeViewModel : 73cb6d85-a8e3-41c2-a4ee-0fe7c2f75677\\\\nInput : B cd27587e-96fa-4de1-a982-11092f6b5101\",\"NodeId\":\"MultiplyNumbersNodeViewModel : 73cb6d85-a8e3-41c2-a4ee-0fe7c2f75677\"}]}],\"MechanicConnectionId\":\"kd_4c22\",\"GateDataType\":2,\"SaveData\":null,\"VisualPosition\":{\"x\":-2000.0,\"y\":-300.0},\"VisualCollapsed\":false,\"ModelVersion\":1,\"Version\":\"0.1\"},{\"Id\":\"RootNodeViewModel : 112f7876-a669-4cb2-9985-9252abd604c6\",\"OperationType\":256,\"Inputs\":[],\"Outputs\":[{\"Id\":\"RootNodeViewModel : 112f7876-a669-4cb2-9985-9252abd604c6\\nOutput : Number cc46478e-65ae-4fd1-9e89-670d703d8e26\",\"DataType\":2,\"ConnectedInputsIds\":[{\"Id\":\"LessNodeViewModel : 0a1c4e0b-9b46-4a5d-80ac-1e5310698de0\\\\nInput : B a2642b3a-e2a1-4001-ad13-95a0815a6b87\",\"NodeId\":\"LessNodeViewModel : 0a1c4e0b-9b46-4a5d-80ac-1e5310698de0\"}]}],\"MechanicConnectionId\":\"brakedistance_4ce2\",\"GateDataType\":2,\"SaveData\":null,\"VisualPosition\":{\"x\":400.0,\"y\":2100.0},\"VisualCollapsed\":false,\"ModelVersion\":1,\"Version\":\"0.1\"},{\"Id\":\"RootNodeViewModel : 891620d8-871c-4dfb-b6b6-3dea1cba575a\",\"OperationType\":256,\"Inputs\":[],\"Outputs\":[{\"Id\":\"RootNodeViewModel : 891620d8-871c-4dfb-b6b6-3dea1cba575a\\nOutput : Number 7654a216-35b1-410e-b530-c48c83027910\",\"DataType\":2,\"ConnectedInputsIds\":[{\"Id\":\"MultiplyNumbersNodeViewModel : c27010c6-e5fd-4abd-981f-d0151c3a3d28\\\\nInput : B f61b8315-ba79-43c9-b600-8e5c50366b5d\",\"NodeId\":\"MultiplyNumbersNodeViewModel : c27010c6-e5fd-4abd-981f-d0151c3a3d28\"},{\"Id\":\"MultiplyNumbersNodeViewModel : 703b17ab-3071-44f3-9d61-9aee82c4594c\\\\nInput : B 43ab7bd8-2603-4d3d-8661-cf05253064d0\",\"NodeId\":\"MultiplyNumbersNodeViewModel : 703b17ab-3071-44f3-9d61-9aee82c4594c\"}]}],\"MechanicConnectionId\":\"brakeaggression_107f\",\"GateDataType\":2,\"SaveData\":null,\"VisualPosition\":{\"x\":-400.0,\"y\":-900.0},\"VisualCollapsed\":false,\"ModelVersion\":1,\"Version\":\"0.1\"},{\"Id\":\"RootNodeViewModel : 22334aad-b49d-440b-b650-2fa26219e893\",\"OperationType\":256,\"Inputs\":[],\"Outputs\":[{\"Id\":\"RootNodeViewModel : 22334aad-b49d-440b-b650-2fa26219e893\\nOutput : Number 4f621300-7204-45e2-bb37-c15af5ed1837\",\"DataType\":2,\"ConnectedInputsIds\":[{\"Id\":\"MultiplyNumbersNodeViewModel : a33673be-e7bb-43d7-b89f-0114bcfaddfa\\\\nInput : B 3f17f96b-4630-47f1-acd9-5365c5207225\",\"NodeId\":\"MultiplyNumbersNodeViewModel : a33673be-e7bb-43d7-b89f-0114bcfaddfa\"}]}],\"MechanicConnectionId\":\"gravity_ba64\",\"GateDataType\":2,\"SaveData\":null,\"VisualPosition\":{\"x\":-1200.0,\"y\":-900.0},\"VisualCollapsed\":false,\"ModelVersion\":1,\"Version\":\"0.1\"},{\"Id\":\"RootNodeViewModel : 5427ad52-5dee-42c6-8955-95d61c475cef\",\"OperationType\":256,\"Inputs\":[],\"Outputs\":[{\"Id\":\"RootNodeViewModel : 5427ad52-5dee-42c6-8955-95d61c475cef\\nOutput : Number 7f4664bb-d0a7-4175-8fdf-c717ea1138df\",\"DataType\":2,\"ConnectedInputsIds\":[{\"Id\":\"AccumulateNodeViewModel : 99975ef7-b192-422b-963d-52f636909294\\\\nInput : Reset 45a5f158-cd17-419b-b102-4e8ab93768c3\",\"NodeId\":\"AccumulateNodeViewModel : 99975ef7-b192-422b-963d-52f636909294\"}]}],\"MechanicConnectionId\":\"resetintegral_55f7\",\"GateDataType\":2,\"SaveData\":null,\"VisualPosition\":{\"x\":-3600.0,\"y\":-1500.0},\"VisualCollapsed\":false,\"ModelVersion\":1,\"Version\":\"0.1\"},{\"Id\":\"TimeNodeViewModel : a0a361c3-9705-4b57-ade7-e3ac68615c37\",\"ModelVersion\":1,\"Version\":\"0.1\",\"OperationType\":260,\"Inputs\":[],\"Outputs\":[{\"Id\":\"TimeNodeViewModel : a0a361c3-9705-4b57-ade7-e3ac68615c37\\\\nOutput : Time d655c5c2-9360-491c-8009-3ed020fcbbfe\",\"DataType\":2,\"ConnectedInputsIds\":[]},{\"Id\":\"TimeNodeViewModel : a0a361c3-9705-4b57-ade7-e3ac68615c37\\\\nOutput : Delta time 6516f64a-93b8-4bee-bbd4-238ec87b26f2\",\"DataType\":2,\"ConnectedInputsIds\":[{\"Id\":\"MultiplyNumbersNodeViewModel : d597653a-4360-408f-835e-d772cecd3385\\\\nInput : B d2290637-febd-4dab-9932-45bd920beb9b\",\"NodeId\":\"MultiplyNumbersNodeViewModel : d597653a-4360-408f-835e-d772cecd3385\"}]},{\"Id\":\"TimeNodeViewModel : a0a361c3-9705-4b57-ade7-e3ac68615c37\\\\nOutput : Sin Time 16ae277a-aee0-4af9-9dd7-822f153cd699\",\"DataType\":2,\"ConnectedInputsIds\":[]},{\"Id\":\"TimeNodeViewModel : a0a361c3-9705-4b57-ade7-e3ac68615c37\\\\nOutput : Cos Time ced41d98-97a4-458b-991d-f6dda21f92d3\",\"DataType\":2,\"ConnectedInputsIds\":[]}],\"VisualPosition\":{\"x\":-4400.0,\"y\":-2100.0},\"VisualCollapsed\":false,\"MechanicConnectionId\":null,\"GateDataType\":0,\"SaveData\":null},{\"Id\":\"ConstantNodeViewModel : 28e12460-6452-4107-9829-5506c734b905\",\"OperationType\":257,\"Inputs\":[],\"Outputs\":[{\"Id\":\"ConstantNodeViewModel : 28e12460-6452-4107-9829-5506c734b905\\nOutput : Number 3de9685f-3f27-40ad-a39e-50bb7fed3065\",\"DataType\":2,\"ConnectedInputsIds\":[{\"Id\":\"BranchNodeViewModel : 7aebd9c0-78d6-476d-8a74-d4bba7e3ca19\\\\nInput : B 028958d4-89ad-48b2-8847-48fe1d082e25\",\"NodeId\":\"BranchNodeViewModel : 7aebd9c0-78d6-476d-8a74-d4bba7e3ca19\"},{\"Id\":\"CombineVectorNodeViewModel : 5b12f256-c962-4392-86eb-abed1b7bcb43\\\\nInput : X b10ed6c8-c373-418f-8401-2c6a38627cdb\",\"NodeId\":\"CombineVectorNodeViewModel : 5b12f256-c962-4392-86eb-abed1b7bcb43\"},{\"Id\":\"CombineVectorNodeViewModel : 5b12f256-c962-4392-86eb-abed1b7bcb43\\\\nInput : Z 333cfa55-1678-4dba-a553-e17b889fc479\",\"NodeId\":\"CombineVectorNodeViewModel : 5b12f256-c962-4392-86eb-abed1b7bcb43\"},{\"Id\":\"CombineVectorNodeViewModel : 5b12f256-c962-4392-86eb-abed1b7bcb43\\\\nInput : W 18c88ab5-ec8c-42b6-b222-21b0e75441f8\",\"NodeId\":\"CombineVectorNodeViewModel : 5b12f256-c962-4392-86eb-abed1b7bcb43\"}]}],\"MechanicConnectionId\":null,\"GateDataType\":2,\"SaveData\":\"{\\\"DataValue\\\": \\\"0.0\\\"}\",\"VisualPosition\":{\"x\":1200.0,\"y\":-2100.0},\"VisualCollapsed\":false,\"ModelVersion\":1,\"Version\":\"0.1\"},{\"Id\":\"ConstantNodeViewModel : d9886922-637a-43ae-83c3-4dab17805996\",\"OperationType\":257,\"Inputs\":[],\"Outputs\":[{\"Id\":\"ConstantNodeViewModel : d9886922-637a-43ae-83c3-4dab17805996\\nOutput : Number 4b50e942-d6b3-4130-af10-c8bf056568fa\",\"DataType\":2,\"ConnectedInputsIds\":[{\"Id\":\"MultiplyNumbersNodeViewModel : 6293058c-97d1-4bb3-805e-4a90c21920a5\\\\nInput : B ed0bdd86-5639-4233-8899-e3b1eaf73495\",\"NodeId\":\"MultiplyNumbersNodeViewModel : 6293058c-97d1-4bb3-805e-4a90c21920a5\"}]}],\"MechanicConnectionId\":null,\"GateDataType\":2,\"SaveData\":\"{\\\"DataValue\\\": \\\"-1.0\\\"}\",\"VisualPosition\":{\"x\":400.0,\"y\":1500.0},\"VisualCollapsed\":false,\"ModelVersion\":1,\"Version\":\"0.1\"},{\"Id\":\"PositionEntityNodeViewModel : bb346c15-8028-4e53-846c-d9bbe55d62e9\",\"ModelVersion\":1,\"Version\":\"0.1\",\"OperationType\":1559,\"Inputs\":[{\"Id\":\"PositionEntityNodeViewModel : bb346c15-8028-4e53-846c-d9bbe55d62e9\\\\nInput : object c4501880-ef4b-4bfe-bd49-99a95ad40d61\",\"DataType\":1,\"connectedOutputIdModel\":{\"Id\":\"RootNodeViewModel : 022a6f67-b0b8-4000-8f0c-47a4ddb6b8f5\\nOutput : Number 5f50053a-9988-48c8-ba4d-4192305a6578\",\"NodeId\":\"RootNodeViewModel : 022a6f67-b0b8-4000-8f0c-47a4ddb6b8f5\"}},{\"Id\":\"PositionEntityNodeViewModel : bb346c15-8028-4e53-846c-d9bbe55d62e9\\\\nInput : position 25468cfb-578c-4527-bb49-9f60fee5faa3\",\"DataType\":8,\"connectedOutputIdModel\":null}],\"Outputs\":[{\"Id\":\"PositionEntityNodeViewModel : bb346c15-8028-4e53-846c-d9bbe55d62e9\\\\nOutput : position 0986135b-b4dc-43fa-9c9f-8a7617e3f646\",\"DataType\":8,\"ConnectedInputsIds\":[{\"Id\":\"SplitVectorNodeViewModel : 92d722d1-eac9-4f3d-9c0e-227d7b7aa2ad\\\\nInput : Input bb92c1e7-f31a-4f83-9b0d-86ad28c12a01\",\"NodeId\":\"SplitVectorNodeViewModel : 92d722d1-eac9-4f3d-9c0e-227d7b7aa2ad\"}]}],\"VisualPosition\":{\"x\":-2000.0,\"y\":-2100.0},\"VisualCollapsed\":false,\"MechanicConnectionId\":null,\"GateDataType\":0,\"SaveData\":null},{\"Id\":\"VelocityEntityNodeViewModel : 087d34ce-5f0a-4d5d-b0a3-5a03559b323b\",\"ModelVersion\":1,\"Version\":\"0.1\",\"OperationType\":1538,\"Inputs\":[{\"Id\":\"VelocityEntityNodeViewModel : 087d34ce-5f0a-4d5d-b0a3-5a03559b323b\\\\nInput : object 5a4c6c30-0b63-4362-938b-9819966d1a82\",\"DataType\":1,\"connectedOutputIdModel\":{\"Id\":\"RootNodeViewModel : 022a6f67-b0b8-4000-8f0c-47a4ddb6b8f5\\nOutput : Number 5f50053a-9988-48c8-ba4d-4192305a6578\",\"NodeId\":\"RootNodeViewModel : 022a6f67-b0b8-4000-8f0c-47a4ddb6b8f5\"}},{\"Id\":\"VelocityEntityNodeViewModel : 087d34ce-5f0a-4d5d-b0a3-5a03559b323b\\\\nInput : Velocity bcd6b4e0-f6b9-4858-989c-74ca8d368ccd\",\"DataType\":8,\"connectedOutputIdModel\":null}],\"Outputs\":[{\"Id\":\"VelocityEntityNodeViewModel : 087d34ce-5f0a-4d5d-b0a3-5a03559b323b\\\\nOutput : Velocity 23758e74-697f-4c76-ab85-27c563a79f6c\",\"DataType\":8,\"ConnectedInputsIds\":[{\"Id\":\"SplitVectorNodeViewModel : c890160d-8dae-4aaa-9b9d-3bb10d71bd32\\\\nInput : Input ac20937e-34bb-4941-90dd-310ada2599e2\",\"NodeId\":\"SplitVectorNodeViewModel : c890160d-8dae-4aaa-9b9d-3bb10d71bd32\"}]}],\"VisualPosition\":{\"x\":-1200.0,\"y\":1500.0},\"VisualCollapsed\":false,\"MechanicConnectionId\":null,\"GateDataType\":0,\"SaveData\":null},{\"Id\":\"MassEntityNodeViewModel : e64f2c05-7909-49f9-ad63-346227051a8f\",\"ModelVersion\":1,\"Version\":\"0.1\",\"OperationType\":1557,\"Inputs\":[{\"Id\":\"MassEntityNodeViewModel : e64f2c05-7909-49f9-ad63-346227051a8f\\\\nInput : object 4773710b-542d-418a-b0f1-c937672ff67d\",\"DataType\":1,\"connectedOutputIdModel\":{\"Id\":\"RootNodeViewModel : 022a6f67-b0b8-4000-8f0c-47a4ddb6b8f5\\nOutput : Number 5f50053a-9988-48c8-ba4d-4192305a6578\",\"NodeId\":\"RootNodeViewModel : 022a6f67-b0b8-4000-8f0c-47a4ddb6b8f5\"}}],\"Outputs\":[{\"Id\":\"MassEntityNodeViewModel : e64f2c05-7909-49f9-ad63-346227051a8f\\\\nOutput : Mass f032ea0f-10a0-4aee-873f-f60cc467bd2c\",\"DataType\":2,\"ConnectedInputsIds\":[{\"Id\":\"MultiplyNumbersNodeViewModel : a33673be-e7bb-43d7-b89f-0114bcfaddfa\\\\nInput : A 92d96ce1-e4e6-4555-9793-b012e711813f\",\"NodeId\":\"MultiplyNumbersNodeViewModel : a33673be-e7bb-43d7-b89f-0114bcfaddfa\"}]}],\"VisualPosition\":{\"x\":-1200.0,\"y\":-1500.0},\"VisualCollapsed\":false,\"MechanicConnectionId\":null,\"GateDataType\":0,\"SaveData\":null},{\"Id\":\"SplitVectorNodeViewModel : 7553a9ea-0c6a-4ab1-b869-db5b8bb1ce29\",\"ModelVersion\":1,\"Version\":\"0.1\",\"OperationType\":1280,\"Inputs\":[{\"Id\":\"SplitVectorNodeViewModel : 7553a9ea-0c6a-4ab1-b869-db5b8bb1ce29\\\\nInput : Input b961996c-9743-4b91-89f0-1b35cd1d9f2c\",\"DataType\":8,\"connectedOutputIdModel\":{\"Id\":\"RootNodeViewModel : 1cd4a012-4386-41c1-a1a2-89d3620d5f6f\\nOutput : Number 26610507-63a6-4560-b882-232bd92c3087\",\"NodeId\":\"RootNodeViewModel : 1cd4a012-4386-41c1-a1a2-89d3620d5f6f\"}}],\"Outputs\":[{\"Id\":\"SplitVectorNodeViewModel : 7553a9ea-0c6a-4ab1-b869-db5b8bb1ce29\\\\nOutput : X fad62503-6495-4192-9808-7465699dd73c\",\"DataType\":2,\"ConnectedInputsIds\":[]},{\"Id\":\"SplitVectorNodeViewModel : 7553a9ea-0c6a-4ab1-b869-db5b8bb1ce29\\\\nOutput : Y d0c2c571-dc32-4edb-8439-54f063879ea6\",\"DataType\":2,\"ConnectedInputsIds\":[{\"Id\":\"SubtractNumbersNodeViewModel : 0928fcbe-0907-4c7f-a0c6-26f550a8c08c\\\\nInput : A 0aa412c5-15e0-48e8-8ce9-85516bffaeaf\",\"NodeId\":\"SubtractNumbersNodeViewModel : 0928fcbe-0907-4c7f-a0c6-26f550a8c08c\"}]},{\"Id\":\"SplitVectorNodeViewModel : 7553a9ea-0c6a-4ab1-b869-db5b8bb1ce29\\\\nOutput : Z bbed1065-fded-407f-ae96-9abd824ab146\",\"DataType\":2,\"ConnectedInputsIds\":[]},{\"Id\":\"SplitVectorNodeViewModel : 7553a9ea-0c6a-4ab1-b869-db5b8bb1ce29\\\\nOutput : W b9347393-3f81-4933-a07d-d19575f5665f\",\"DataType\":2,\"ConnectedInputsIds\":[]}],\"VisualPosition\":{\"x\":-1200.0,\"y\":900.0},\"VisualCollapsed\":false,\"MechanicConnectionId\":null,\"GateDataType\":2,\"SaveData\":null},{\"Id\":\"SplitVectorNodeViewModel : 92d722d1-eac9-4f3d-9c0e-227d7b7aa2ad\",\"ModelVersion\":1,\"Version\":\"0.1\",\"OperationType\":1280,\"Inputs\":[{\"Id\":\"SplitVectorNodeViewModel : 92d722d1-eac9-4f3d-9c0e-227d7b7aa2ad\\\\nInput : Input bb92c1e7-f31a-4f83-9b0d-86ad28c12a01\",\"DataType\":8,\"connectedOutputIdModel\":{\"Id\":\"PositionEntityNodeViewModel : bb346c15-8028-4e53-846c-d9bbe55d62e9\\\\nOutput : position 0986135b-b4dc-43fa-9c9f-8a7617e3f646\",\"NodeId\":\"PositionEntityNodeViewModel : bb346c15-8028-4e53-846c-d9bbe55d62e9\"}}],\"Outputs\":[{\"Id\":\"SplitVectorNodeViewModel : 92d722d1-eac9-4f3d-9c0e-227d7b7aa2ad\\\\nOutput : X af76d2ae-93de-4942-b8e3-430849c1e36e\",\"DataType\":2,\"ConnectedInputsIds\":[]},{\"Id\":\"SplitVectorNodeViewModel : 92d722d1-eac9-4f3d-9c0e-227d7b7aa2ad\\\\nOutput : Y 89f98563-a9f5-4088-b70a-83c1664f8aef\",\"DataType\":2,\"ConnectedInputsIds\":[{\"Id\":\"SubtractNumbersNodeViewModel : 0928fcbe-0907-4c7f-a0c6-26f550a8c08c\\\\nInput : B db7dc59a-b090-4a71-8b16-96e914d155a2\",\"NodeId\":\"SubtractNumbersNodeViewModel : 0928fcbe-0907-4c7f-a0c6-26f550a8c08c\"}]},{\"Id\":\"SplitVectorNodeViewModel : 92d722d1-eac9-4f3d-9c0e-227d7b7aa2ad\\\\nOutput : Z 3f4efde8-1687-4539-b790-b0798bd9da64\",\"DataType\":2,\"ConnectedInputsIds\":[]},{\"Id\":\"SplitVectorNodeViewModel : 92d722d1-eac9-4f3d-9c0e-227d7b7aa2ad\\\\nOutput : W 4081f01b-d2c2-478c-a03e-5c89f2ce995c\",\"DataType\":2,\"ConnectedInputsIds\":[]}],\"VisualPosition\":{\"x\":-1200.0,\"y\":-2100.0},\"VisualCollapsed\":false,\"MechanicConnectionId\":null,\"GateDataType\":2,\"SaveData\":null},{\"Id\":\"SplitVectorNodeViewModel : c890160d-8dae-4aaa-9b9d-3bb10d71bd32\",\"ModelVersion\":1,\"Version\":\"0.1\",\"OperationType\":1280,\"Inputs\":[{\"Id\":\"SplitVectorNodeViewModel : c890160d-8dae-4aaa-9b9d-3bb10d71bd32\\\\nInput : Input ac20937e-34bb-4941-90dd-310ada2599e2\",\"DataType\":8,\"connectedOutputIdModel\":{\"Id\":\"VelocityEntityNodeViewModel : 087d34ce-5f0a-4d5d-b0a3-5a03559b323b\\\\nOutput : Velocity 23758e74-697f-4c76-ab85-27c563a79f6c\",\"NodeId\":\"VelocityEntityNodeViewModel : 087d34ce-5f0a-4d5d-b0a3-5a03559b323b\"}}],\"Outputs\":[{\"Id\":\"SplitVectorNodeViewModel : c890160d-8dae-4aaa-9b9d-3bb10d71bd32\\\\nOutput : X 68a11ae6-08fd-4ff4-9d0d-de12466c2b94\",\"DataType\":2,\"ConnectedInputsIds\":[]},{\"Id\":\"SplitVectorNodeViewModel : c890160d-8dae-4aaa-9b9d-3bb10d71bd32\\\\nOutput : Y bb731f45-21ea-46ca-aa24-187a551a7b89\",\"DataType\":2,\"ConnectedInputsIds\":[{\"Id\":\"MultiplyNumbersNodeViewModel : 73cb6d85-a8e3-41c2-a4ee-0fe7c2f75677\\\\nInput : A 6a06af45-0545-41eb-9e6f-3a2d8d4c7b7c\",\"NodeId\":\"MultiplyNumbersNodeViewModel : 73cb6d85-a8e3-41c2-a4ee-0fe7c2f75677\"},{\"Id\":\"MassEntityNodeViewModel : 3f1e9335-332a-488d-be37-aba20943a867\\\\nInput : object 7558dbb5-c337-4ee2-8b6e-ee1206349573\",\"NodeId\":\"MassEntityNodeViewModel : 3f1e9335-332a-488d-be37-aba20943a867\"},{\"Id\":\"MultiplyNumbersNodeViewModel : 703b17ab-3071-44f3-9d61-9aee82c4594c\\\\nInput : A 1c5d05d1-d5b0-45c6-b5c9-86311ccab2ec\",\"NodeId\":\"MultiplyNumbersNodeViewModel : 703b17ab-3071-44f3-9d61-9aee82c4594c\"}]},{\"Id\":\"SplitVectorNodeViewModel : c890160d-8dae-4aaa-9b9d-3bb10d71bd32\\\\nOutput : Z 60fff7e3-dc8d-4671-9a57-978a4bac1787\",\"DataType\":2,\"ConnectedInputsIds\":[]},{\"Id\":\"SplitVectorNodeViewModel : c890160d-8dae-4aaa-9b9d-3bb10d71bd32\\\\nOutput : W 5ff454d4-6f62-434e-b2a5-c6f6c0c73038\",\"DataType\":2,\"ConnectedInputsIds\":[]}],\"VisualPosition\":{\"x\":-2000.0,\"y\":300.0},\"VisualCollapsed\":false,\"MechanicConnectionId\":null,\"GateDataType\":2,\"SaveData\":null},{\"Id\":\"SubtractNumbersNodeViewModel : 0928fcbe-0907-4c7f-a0c6-26f550a8c08c\",\"ModelVersion\":1,\"Version\":\"0.1\",\"OperationType\":2305,\"Inputs\":[{\"Id\":\"SubtractNumbersNodeViewModel : 0928fcbe-0907-4c7f-a0c6-26f550a8c08c\\\\nInput : A 0aa412c5-15e0-48e8-8ce9-85516bffaeaf\",\"DataType\":2,\"connectedOutputIdModel\":{\"Id\":\"SplitVectorNodeViewModel : 7553a9ea-0c6a-4ab1-b869-db5b8bb1ce29\\\\nOutput : Y d0c2c571-dc32-4edb-8439-54f063879ea6\",\"NodeId\":\"SplitVectorNodeViewModel : 7553a9ea-0c6a-4ab1-b869-db5b8bb1ce29\"}},{\"Id\":\"SubtractNumbersNodeViewModel : 0928fcbe-0907-4c7f-a0c6-26f550a8c08c\\\\nInput : B db7dc59a-b090-4a71-8b16-96e914d155a2\",\"DataType\":2,\"connectedOutputIdModel\":{\"Id\":\"SplitVectorNodeViewModel : 92d722d1-eac9-4f3d-9c0e-227d7b7aa2ad\\\\nOutput : Y 89f98563-a9f5-4088-b70a-83c1664f8aef\",\"NodeId\":\"SplitVectorNodeViewModel : 92d722d1-eac9-4f3d-9c0e-227d7b7aa2ad\"}}],\"Outputs\":[{\"Id\":\"SubtractNumbersNodeViewModel : 0928fcbe-0907-4c7f-a0c6-26f550a8c08c\\\\nOutput : A - B a5aa5a10-e16b-4482-8d3b-86b668d5bda9\",\"DataType\":2,\"ConnectedInputsIds\":[{\"Id\":\"MultiplyNumbersNodeViewModel : aa4e292a-2645-4468-9eb1-5908b7390585\\\\nInput : A 3cfa36ae-8ee4-4f5d-9297-41c59d785d6d\",\"NodeId\":\"MultiplyNumbersNodeViewModel : aa4e292a-2645-4468-9eb1-5908b7390585\"},{\"Id\":\"MultiplyNumbersNodeViewModel : d597653a-4360-408f-835e-d772cecd3385\\\\nInput : A 7b47591a-1606-40b1-8087-fe874fd6a0b8\",\"NodeId\":\"MultiplyNumbersNodeViewModel : d597653a-4360-408f-835e-d772cecd3385\"},{\"Id\":\"MassEntityNodeViewModel : 95cdc2ad-db23-49f4-94f2-fa4baea6c90b\\\\nInput : object 061dbb10-3ae3-4d2a-b6cf-d831e56d412e\",\"NodeId\":\"MassEntityNodeViewModel : 95cdc2ad-db23-49f4-94f2-fa4baea6c90b\"}]}],\"VisualPosition\":{\"x\":-4400.0,\"y\":-1500.0},\"VisualCollapsed\":false,\"MechanicConnectionId\":null,\"GateDataType\":2,\"SaveData\":null},{\"Id\":\"MultiplyNumbersNodeViewModel : aa4e292a-2645-4468-9eb1-5908b7390585\",\"ModelVersion\":1,\"Version\":\"0.1\",\"OperationType\":2306,\"Inputs\":[{\"Id\":\"MultiplyNumbersNodeViewModel : aa4e292a-2645-4468-9eb1-5908b7390585\\\\nInput : A 3cfa36ae-8ee4-4f5d-9297-41c59d785d6d\",\"DataType\":2,\"connectedOutputIdModel\":{\"Id\":\"SubtractNumbersNodeViewModel : 0928fcbe-0907-4c7f-a0c6-26f550a8c08c\\\\nOutput : A - B a5aa5a10-e16b-4482-8d3b-86b668d5bda9\",\"NodeId\":\"SubtractNumbersNodeViewModel : 0928fcbe-0907-4c7f-a0c6-26f550a8c08c\"}},{\"Id\":\"MultiplyNumbersNodeViewModel : aa4e292a-2645-4468-9eb1-5908b7390585\\\\nInput : B 0486808c-bd6b-48f1-a0cf-b013d2a9d96a\",\"DataType\":2,\"connectedOutputIdModel\":{\"Id\":\"RootNodeViewModel : 57eea8e8-0905-4271-bd85-8a1841ed9b20\\nOutput : Number f857ebc8-1bcc-418a-bf02-13729840f813\",\"NodeId\":\"RootNodeViewModel : 57eea8e8-0905-4271-bd85-8a1841ed9b20\"}}],\"Outputs\":[{\"Id\":\"MultiplyNumbersNodeViewModel : aa4e292a-2645-4468-9eb1-5908b7390585\\\\nOutput : A \\u00d7 B 9ee7c9ce-b97b-44b6-a3b0-e99f20428475\",\"DataType\":2,\"ConnectedInputsIds\":[{\"Id\":\"AddNumbersNodeViewModel : c967f8d1-8dde-41f5-a552-2e4ff04cf028\\\\nInput : A 8af63aaf-c2d4-4091-9fdb-ae3110f4658f\",\"NodeId\":\"AddNumbersNodeViewModel : c967f8d1-8dde-41f5-a552-2e4ff04cf028\"}]}],\"VisualPosition\":{\"x\":-2000.0,\"y\":-1500.0},\"VisualCollapsed\":false,\"MechanicConnectionId\":null,\"GateDataType\":2,\"SaveData\":null},{\"Id\":\"MultiplyNumbersNodeViewModel : d597653a-4360-408f-835e-d772cecd3385\",\"ModelVersion\":1,\"Version\":\"0.1\",\"OperationType\":2306,\"Inputs\":[{\"Id\":\"MultiplyNumbersNodeViewModel : d597653a-4360-408f-835e-d772cecd3385\\\\nInput : A 7b47591a-1606-40b1-8087-fe874fd6a0b8\",\"DataType\":2,\"connectedOutputIdModel\":{\"Id\":\"SubtractNumbersNodeViewModel : 0928fcbe-0907-4c7f-a0c6-26f550a8c08c\\\\nOutput : A - B a5aa5a10-e16b-4482-8d3b-86b668d5bda9\",\"NodeId\":\"SubtractNumbersNodeViewModel : 0928fcbe-0907-4c7f-a0c6-26f550a8c08c\"}},{\"Id\":\"MultiplyNumbersNodeViewModel : d597653a-4360-408f-835e-d772cecd3385\\\\nInput : B d2290637-febd-4dab-9932-45bd920beb9b\",\"DataType\":2,\"connectedOutputIdModel\":{\"Id\":\"TimeNodeViewModel : a0a361c3-9705-4b57-ade7-e3ac68615c37\\\\nOutput : Delta time 6516f64a-93b8-4bee-bbd4-238ec87b26f2\",\"NodeId\":\"TimeNodeViewModel : a0a361c3-9705-4b57-ade7-e3ac68615c37\"}}],\"Outputs\":[{\"Id\":\"MultiplyNumbersNodeViewModel : d597653a-4360-408f-835e-d772cecd3385\\\\nOutput : A \\u00d7 B feddd6ad-7a13-4e3d-a2a3-3a4e565aaa85\",\"DataType\":2,\"ConnectedInputsIds\":[{\"Id\":\"AccumulateNodeViewModel : 99975ef7-b192-422b-963d-52f636909294\\\\nInput : Number 2c25103c-ca0e-4f94-b723-bc6dccbf9bc4\",\"NodeId\":\"AccumulateNodeViewModel : 99975ef7-b192-422b-963d-52f636909294\"}]}],\"VisualPosition\":{\"x\":-3600.0,\"y\":-2100.0},\"VisualCollapsed\":false,\"MechanicConnectionId\":null,\"GateDataType\":2,\"SaveData\":null},{\"Id\":\"AccumulateNodeViewModel : 99975ef7-b192-422b-963d-52f636909294\",\"ModelVersion\":1,\"Version\":\"0.1\",\"OperationType\":4100,\"Inputs\":[{\"Id\":\"AccumulateNodeViewModel : 99975ef7-b192-422b-963d-52f636909294\\\\nInput : Number 2c25103c-ca0e-4f94-b723-bc6dccbf9bc4\",\"DataType\":2,\"connectedOutputIdModel\":{\"Id\":\"MultiplyNumbersNodeViewModel : d597653a-4360-408f-835e-d772cecd3385\\\\nOutput : A \\u00d7 B feddd6ad-7a13-4e3d-a2a3-3a4e565aaa85\",\"NodeId\":\"MultiplyNumbersNodeViewModel : d597653a-4360-408f-835e-d772cecd3385\"}},{\"Id\":\"AccumulateNodeViewModel : 99975ef7-b192-422b-963d-52f636909294\\\\nInput : Reset 45a5f158-cd17-419b-b102-4e8ab93768c3\",\"DataType\":2,\"connectedOutputIdModel\":{\"Id\":\"RootNodeViewModel : 5427ad52-5dee-42c6-8955-95d61c475cef\\nOutput : Number 7f4664bb-d0a7-4175-8fdf-c717ea1138df\",\"NodeId\":\"RootNodeViewModel : 5427ad52-5dee-42c6-8955-95d61c475cef\"}}],\"Outputs\":[{\"Id\":\"AccumulateNodeViewModel : 99975ef7-b192-422b-963d-52f636909294\\\\nOutput : Total d85b7b58-cb90-4306-876a-cf8cb7aea4ae\",\"DataType\":2,\"ConnectedInputsIds\":[{\"Id\":\"MultiplyNumbersNodeViewModel : 18cf38ce-71c6-4cb2-99f3-d8390b4d0ef2\\\\nInput : A a2ea134b-756c-4f44-b4a1-6ce3dd3af48c\",\"NodeId\":\"MultiplyNumbersNodeViewModel : 18cf38ce-71c6-4cb2-99f3-d8390b4d0ef2\"}]}],\"VisualPosition\":{\"x\":-2800.0,\"y\":-900.0},\"VisualCollapsed\":false,\"MechanicConnectionId\":null,\"GateDataType\":2,\"SaveData\":null},{\"Id\":\"MultiplyNumbersNodeViewModel : 18cf38ce-71c6-4cb2-99f3-d8390b4d0ef2\",\"ModelVersion\":1,\"Version\":\"0.1\",\"OperationType\":2306,\"Inputs\":[{\"Id\":\"MultiplyNumbersNodeViewModel : 18cf38ce-71c6-4cb2-99f3-d8390b4d0ef2\\\\nInput : A a2ea134b-756c-4f44-b4a1-6ce3dd3af48c\",\"DataType\":2,\"connectedOutputIdModel\":{\"Id\":\"AccumulateNodeViewModel : 99975ef7-b192-422b-963d-52f636909294\\\\nOutput : Total d85b7b58-cb90-4306-876a-cf8cb7aea4ae\",\"NodeId\":\"AccumulateNodeViewModel : 99975ef7-b192-422b-963d-52f636909294\"}},{\"Id\":\"MultiplyNumbersNodeViewModel : 18cf38ce-71c6-4cb2-99f3-d8390b4d0ef2\\\\nInput : B e869ab3b-404d-4ec6-9e25-cc0f12301fb7\",\"DataType\":2,\"connectedOutputIdModel\":{\"Id\":\"RootNodeViewModel : f82094b8-28ff-464a-8fd5-b91ee6e9887c\\nOutput : Number 1d8f6e84-9336-4fef-be29-671962ebe0f1\",\"NodeId\":\"RootNodeViewModel : f82094b8-28ff-464a-8fd5-b91ee6e9887c\"}}],\"Outputs\":[{\"Id\":\"MultiplyNumbersNodeViewModel : 18cf38ce-71c6-4cb2-99f3-d8390b4d0ef2\\\\nOutput : A \\u00d7 B 505fb302-fcd5-43b9-9133-4d17344095c2\",\"DataType\":2,\"ConnectedInputsIds\":[{\"Id\":\"AddNumbersNodeViewModel : c967f8d1-8dde-41f5-a552-2e4ff04cf028\\\\nInput : B 4ca66653-7d8f-46d2-ab31-73f6e05f1a02\",\"NodeId\":\"AddNumbersNodeViewModel : c967f8d1-8dde-41f5-a552-2e4ff04cf028\"}]}],\"VisualPosition\":{\"x\":-2000.0,\"y\":-900.0},\"VisualCollapsed\":false,\"MechanicConnectionId\":null,\"GateDataType\":2,\"SaveData\":null},{\"Id\":\"MultiplyNumbersNodeViewModel : 73cb6d85-a8e3-41c2-a4ee-0fe7c2f75677\",\"ModelVersion\":1,\"Version\":\"0.1\",\"OperationType\":2306,\"Inputs\":[{\"Id\":\"MultiplyNumbersNodeViewModel : 73cb6d85-a8e3-41c2-a4ee-0fe7c2f75677\\\\nInput : A 6a06af45-0545-41eb-9e6f-3a2d8d4c7b7c\",\"DataType\":2,\"connectedOutputIdModel\":{\"Id\":\"SplitVectorNodeViewModel : c890160d-8dae-4aaa-9b9d-3bb10d71bd32\\\\nOutput : Y bb731f45-21ea-46ca-aa24-187a551a7b89\",\"NodeId\":\"SplitVectorNodeViewModel : c890160d-8dae-4aaa-9b9d-3bb10d71bd32\"}},{\"Id\":\"MultiplyNumbersNodeViewModel : 73cb6d85-a8e3-41c2-a4ee-0fe7c2f75677\\\\nInput : B cd27587e-96fa-4de1-a982-11092f6b5101\",\"DataType\":2,\"connectedOutputIdModel\":{\"Id\":\"RootNodeViewModel : 5d74f93c-448b-484b-9f75-6a82da73d521\\nOutput : Number a559cbd6-7fd7-434d-a54c-26beda9f7bcd\",\"NodeId\":\"RootNodeViewModel : 5d74f93c-448b-484b-9f75-6a82da73d521\"}}],\"Outputs\":[{\"Id\":\"MultiplyNumbersNodeViewModel : 73cb6d85-a8e3-41c2-a4ee-0fe7c2f75677\\\\nOutput : A \\u00d7 B b0e09be7-9087-4495-a2f8-5d44cb2ce126\",\"DataType\":2,\"ConnectedInputsIds\":[{\"Id\":\"SubtractNumbersNodeViewModel : 821ad593-fc8d-4d68-9f66-958655dd2e0c\\\\nInput : B 26f2bf9f-2556-4a6d-8057-b0c72f171112\",\"NodeId\":\"SubtractNumbersNodeViewModel : 821ad593-fc8d-4d68-9f66-958655dd2e0c\"}]}],\"VisualPosition\":{\"x\":-1200.0,\"y\":300.0},\"VisualCollapsed\":false,\"MechanicConnectionId\":null,\"GateDataType\":2,\"SaveData\":null},{\"Id\":\"AddNumbersNodeViewModel : c967f8d1-8dde-41f5-a552-2e4ff04cf028\",\"ModelVersion\":1,\"Version\":\"0.1\",\"OperationType\":2304,\"Inputs\":[{\"Id\":\"AddNumbersNodeViewModel : c967f8d1-8dde-41f5-a552-2e4ff04cf028\\\\nInput : A 8af63aaf-c2d4-4091-9fdb-ae3110f4658f\",\"DataType\":2,\"connectedOutputIdModel\":{\"Id\":\"MultiplyNumbersNodeViewModel : aa4e292a-2645-4468-9eb1-5908b7390585\\\\nOutput : A \\u00d7 B 9ee7c9ce-b97b-44b6-a3b0-e99f20428475\",\"NodeId\":\"MultiplyNumbersNodeViewModel : aa4e292a-2645-4468-9eb1-5908b7390585\"}},{\"Id\":\"AddNumbersNodeViewModel : c967f8d1-8dde-41f5-a552-2e4ff04cf028\\\\nInput : B 4ca66653-7d8f-46d2-ab31-73f6e05f1a02\",\"DataType\":2,\"connectedOutputIdModel\":{\"Id\":\"MultiplyNumbersNodeViewModel : 18cf38ce-71c6-4cb2-99f3-d8390b4d0ef2\\\\nOutput : A \\u00d7 B 505fb302-fcd5-43b9-9133-4d17344095c2\",\"NodeId\":\"MultiplyNumbersNodeViewModel : 18cf38ce-71c6-4cb2-99f3-d8390b4d0ef2\"}}],\"Outputs\":[{\"Id\":\"AddNumbersNodeViewModel : c967f8d1-8dde-41f5-a552-2e4ff04cf028\\\\nOutput : A + B 5b1b86b0-7dd9-48b5-b1dc-d8756ef93f21\",\"DataType\":2,\"ConnectedInputsIds\":[{\"Id\":\"SubtractNumbersNodeViewModel : 821ad593-fc8d-4d68-9f66-958655dd2e0c\\\\nInput : A b4b35d20-28c0-43f9-8443-89ac7a5d0809\",\"NodeId\":\"SubtractNumbersNodeViewModel : 821ad593-fc8d-4d68-9f66-958655dd2e0c\"}]}],\"VisualPosition\":{\"x\":-1200.0,\"y\":-300.0},\"VisualCollapsed\":false,\"MechanicConnectionId\":null,\"GateDataType\":2,\"SaveData\":null},{\"Id\":\"SubtractNumbersNodeViewModel : 821ad593-fc8d-4d68-9f66-958655dd2e0c\",\"ModelVersion\":1,\"Version\":\"0.1\",\"OperationType\":2305,\"Inputs\":[{\"Id\":\"SubtractNumbersNodeViewModel : 821ad593-fc8d-4d68-9f66-958655dd2e0c\\\\nInput : A b4b35d20-28c0-43f9-8443-89ac7a5d0809\",\"DataType\":2,\"connectedOutputIdModel\":{\"Id\":\"AddNumbersNodeViewModel : c967f8d1-8dde-41f5-a552-2e4ff04cf028\\\\nOutput : A + B 5b1b86b0-7dd9-48b5-b1dc-d8756ef93f21\",\"NodeId\":\"AddNumbersNodeViewModel : c967f8d1-8dde-41f5-a552-2e4ff04cf028\"}},{\"Id\":\"SubtractNumbersNodeViewModel : 821ad593-fc8d-4d68-9f66-958655dd2e0c\\\\nInput : B 26f2bf9f-2556-4a6d-8057-b0c72f171112\",\"DataType\":2,\"connectedOutputIdModel\":{\"Id\":\"MultiplyNumbersNodeViewModel : 73cb6d85-a8e3-41c2-a4ee-0fe7c2f75677\\\\nOutput : A \\u00d7 B b0e09be7-9087-4495-a2f8-5d44cb2ce126\",\"NodeId\":\"MultiplyNumbersNodeViewModel : 73cb6d85-a8e3-41c2-a4ee-0fe7c2f75677\"}}],\"Outputs\":[{\"Id\":\"SubtractNumbersNodeViewModel : 821ad593-fc8d-4d68-9f66-958655dd2e0c\\\\nOutput : A - B ea87cb42-b84c-4744-b872-40ffdbfe0b80\",\"DataType\":2,\"ConnectedInputsIds\":[{\"Id\":\"AddNumbersNodeViewModel : 0e84f0dd-56d7-4c3a-972b-3d8a91eb5ce5\\\\nInput : A 824c54e7-130c-4a3a-8523-022e4ba884ce\",\"NodeId\":\"AddNumbersNodeViewModel : 0e84f0dd-56d7-4c3a-972b-3d8a91eb5ce5\"}]}],\"VisualPosition\":{\"x\":-400.0,\"y\":-1500.0},\"VisualCollapsed\":false,\"MechanicConnectionId\":null,\"GateDataType\":2,\"SaveData\":null},{\"Id\":\"MultiplyNumbersNodeViewModel : a33673be-e7bb-43d7-b89f-0114bcfaddfa\",\"ModelVersion\":1,\"Version\":\"0.1\",\"OperationType\":2306,\"Inputs\":[{\"Id\":\"MultiplyNumbersNodeViewModel : a33673be-e7bb-43d7-b89f-0114bcfaddfa\\\\nInput : A 92d96ce1-e4e6-4555-9793-b012e711813f\",\"DataType\":2,\"connectedOutputIdModel\":{\"Id\":\"MassEntityNodeViewModel : e64f2c05-7909-49f9-ad63-346227051a8f\\\\nOutput : Mass f032ea0f-10a0-4aee-873f-f60cc467bd2c\",\"NodeId\":\"MassEntityNodeViewModel : e64f2c05-7909-49f9-ad63-346227051a8f\"}},{\"Id\":\"MultiplyNumbersNodeViewModel : a33673be-e7bb-43d7-b89f-0114bcfaddfa\\\\nInput : B 3f17f96b-4630-47f1-acd9-5365c5207225\",\"DataType\":2,\"connectedOutputIdModel\":{\"Id\":\"RootNodeViewModel : 22334aad-b49d-440b-b650-2fa26219e893\\nOutput : Number 4f621300-7204-45e2-bb37-c15af5ed1837\",\"NodeId\":\"RootNodeViewModel : 22334aad-b49d-440b-b650-2fa26219e893\"}}],\"Outputs\":[{\"Id\":\"MultiplyNumbersNodeViewModel : a33673be-e7bb-43d7-b89f-0114bcfaddfa\\\\nOutput : A \\u00d7 B 3d4d307c-5fb6-418a-8754-b4778125d0aa\",\"DataType\":2,\"ConnectedInputsIds\":[{\"Id\":\"AddNumbersNodeViewModel : 0e84f0dd-56d7-4c3a-972b-3d8a91eb5ce5\\\\nInput : B aa40e22b-521e-464a-9e65-7383226bb6ef\",\"NodeId\":\"AddNumbersNodeViewModel : 0e84f0dd-56d7-4c3a-972b-3d8a91eb5ce5\"}]}],\"VisualPosition\":{\"x\":-400.0,\"y\":-2100.0},\"VisualCollapsed\":false,\"MechanicConnectionId\":null,\"GateDataType\":2,\"SaveData\":null},{\"Id\":\"AddNumbersNodeViewModel : 0e84f0dd-56d7-4c3a-972b-3d8a91eb5ce5\",\"ModelVersion\":1,\"Version\":\"0.1\",\"OperationType\":2304,\"Inputs\":[{\"Id\":\"AddNumbersNodeViewModel : 0e84f0dd-56d7-4c3a-972b-3d8a91eb5ce5\\\\nInput : A 824c54e7-130c-4a3a-8523-022e4ba884ce\",\"DataType\":2,\"connectedOutputIdModel\":{\"Id\":\"SubtractNumbersNodeViewModel : 821ad593-fc8d-4d68-9f66-958655dd2e0c\\\\nOutput : A - B ea87cb42-b84c-4744-b872-40ffdbfe0b80\",\"NodeId\":\"SubtractNumbersNodeViewModel : 821ad593-fc8d-4d68-9f66-958655dd2e0c\"}},{\"Id\":\"AddNumbersNodeViewModel : 0e84f0dd-56d7-4c3a-972b-3d8a91eb5ce5\\\\nInput : B aa40e22b-521e-464a-9e65-7383226bb6ef\",\"DataType\":2,\"connectedOutputIdModel\":{\"Id\":\"MultiplyNumbersNodeViewModel : a33673be-e7bb-43d7-b89f-0114bcfaddfa\\\\nOutput : A \\u00d7 B 3d4d307c-5fb6-418a-8754-b4778125d0aa\",\"NodeId\":\"MultiplyNumbersNodeViewModel : a33673be-e7bb-43d7-b89f-0114bcfaddfa\"}}],\"Outputs\":[{\"Id\":\"AddNumbersNodeViewModel : 0e84f0dd-56d7-4c3a-972b-3d8a91eb5ce5\\\\nOutput : A + B f042fc1d-2bef-44d0-8792-f74fc2305018\",\"DataType\":2,\"ConnectedInputsIds\":[{\"Id\":\"AddNumbersNodeViewModel : 90a3f2a8-dab3-47d3-a7f0-60c2943bd21d\\\\nInput : A 446fe98c-a8ca-4b71-a694-ff8c5e076456\",\"NodeId\":\"AddNumbersNodeViewModel : 90a3f2a8-dab3-47d3-a7f0-60c2943bd21d\"}]}],\"VisualPosition\":{\"x\":400.0,\"y\":-2100.0},\"VisualCollapsed\":false,\"MechanicConnectionId\":null,\"GateDataType\":2,\"SaveData\":null},{\"Id\":\"MassEntityNodeViewModel : 95cdc2ad-db23-49f4-94f2-fa4baea6c90b\",\"ModelVersion\":1,\"Version\":\"0.1\",\"OperationType\":1557,\"Inputs\":[{\"Id\":\"MassEntityNodeViewModel : 95cdc2ad-db23-49f4-94f2-fa4baea6c90b\\\\nInput : object 061dbb10-3ae3-4d2a-b6cf-d831e56d412e\",\"DataType\":1,\"connectedOutputIdModel\":{\"Id\":\"SubtractNumbersNodeViewModel : 0928fcbe-0907-4c7f-a0c6-26f550a8c08c\\\\nOutput : A - B a5aa5a10-e16b-4482-8d3b-86b668d5bda9\",\"NodeId\":\"SubtractNumbersNodeViewModel : 0928fcbe-0907-4c7f-a0c6-26f550a8c08c\"}}],\"Outputs\":[{\"Id\":\"MassEntityNodeViewModel : 95cdc2ad-db23-49f4-94f2-fa4baea6c90b\\\\nOutput : Mass 2176a8ea-2025-4e0b-a884-5465fbe7823c\",\"DataType\":2,\"ConnectedInputsIds\":[{\"Id\":\"LessNodeViewModel : 0a1c4e0b-9b46-4a5d-80ac-1e5310698de0\\\\nInput : A e65fbf55-c8c1-4c35-980d-eae4a0e35cbc\",\"NodeId\":\"LessNodeViewModel : 0a1c4e0b-9b46-4a5d-80ac-1e5310698de0\"},{\"Id\":\"SqrNodeViewModel : e5faaaec-f19b-4253-98d5-308b874d6d72\\\\nInput : Input 57b4221e-313f-453d-b329-c14a64720705\",\"NodeId\":\"SqrNodeViewModel : e5faaaec-f19b-4253-98d5-308b874d6d72\"}]}],\"VisualPosition\":{\"x\":400.0,\"y\":900.0},\"VisualCollapsed\":false,\"MechanicConnectionId\":null,\"GateDataType\":0,\"SaveData\":null},{\"Id\":\"LessNodeViewModel : 0a1c4e0b-9b46-4a5d-80ac-1e5310698de0\",\"ModelVersion\":1,\"Version\":\"0.1\",\"OperationType\":2821,\"Inputs\":[{\"Id\":\"LessNodeViewModel : 0a1c4e0b-9b46-4a5d-80ac-1e5310698de0\\\\nInput : A e65fbf55-c8c1-4c35-980d-eae4a0e35cbc\",\"DataType\":2,\"connectedOutputIdModel\":{\"Id\":\"MassEntityNodeViewModel : 95cdc2ad-db23-49f4-94f2-fa4baea6c90b\\\\nOutput : Mass 2176a8ea-2025-4e0b-a884-5465fbe7823c\",\"NodeId\":\"MassEntityNodeViewModel : 95cdc2ad-db23-49f4-94f2-fa4baea6c90b\"}},{\"Id\":\"LessNodeViewModel : 0a1c4e0b-9b46-4a5d-80ac-1e5310698de0\\\\nInput : B a2642b3a-e2a1-4001-ad13-95a0815a6b87\",\"DataType\":2,\"connectedOutputIdModel\":{\"Id\":\"RootNodeViewModel : 112f7876-a669-4cb2-9985-9252abd604c6\\nOutput : Number cc46478e-65ae-4fd1-9e89-670d703d8e26\",\"NodeId\":\"RootNodeViewModel : 112f7876-a669-4cb2-9985-9252abd604c6\"}}],\"Outputs\":[{\"Id\":\"LessNodeViewModel : 0a1c4e0b-9b46-4a5d-80ac-1e5310698de0\\\\nOutput : Result 930f487b-8dbb-4ef4-b1d7-f1ff554d8a7f\",\"DataType\":2,\"ConnectedInputsIds\":[{\"Id\":\"AndNodeViewModel : 7d8f7921-2f40-47db-98b2-360de425ae97\\\\nInput : A 2f0c32d8-fa40-40a3-a71a-983a51c082b0\",\"NodeId\":\"AndNodeViewModel : 7d8f7921-2f40-47db-98b2-360de425ae97\"}]}],\"VisualPosition\":{\"x\":1200.0,\"y\":2100.0},\"VisualCollapsed\":false,\"MechanicConnectionId\":null,\"GateDataType\":2,\"SaveData\":null},{\"Id\":\"SqrNodeViewModel : e5faaaec-f19b-4253-98d5-308b874d6d72\",\"ModelVersion\":1,\"Version\":\"0.1\",\"OperationType\":2321,\"Inputs\":[{\"Id\":\"SqrNodeViewModel : e5faaaec-f19b-4253-98d5-308b874d6d72\\\\nInput : Input 57b4221e-313f-453d-b329-c14a64720705\",\"DataType\":2,\"connectedOutputIdModel\":{\"Id\":\"MassEntityNodeViewModel : 95cdc2ad-db23-49f4-94f2-fa4baea6c90b\\\\nOutput : Mass 2176a8ea-2025-4e0b-a884-5465fbe7823c\",\"NodeId\":\"MassEntityNodeViewModel : 95cdc2ad-db23-49f4-94f2-fa4baea6c90b\"}}],\"Outputs\":[{\"Id\":\"SqrNodeViewModel : e5faaaec-f19b-4253-98d5-308b874d6d72\\\\nOutput : Result 2c0181b1-7d22-4284-a3b6-a16adb3c2cb6\",\"DataType\":2,\"ConnectedInputsIds\":[{\"Id\":\"MultiplyNumbersNodeViewModel : c27010c6-e5fd-4abd-981f-d0151c3a3d28\\\\nInput : A 1bd888b2-0487-4976-9ac0-d1f543a72f07\",\"NodeId\":\"MultiplyNumbersNodeViewModel : c27010c6-e5fd-4abd-981f-d0151c3a3d28\"}]}],\"VisualPosition\":{\"x\":1200.0,\"y\":900.0},\"VisualCollapsed\":false,\"MechanicConnectionId\":null,\"GateDataType\":2,\"SaveData\":null},{\"Id\":\"MultiplyNumbersNodeViewModel : c27010c6-e5fd-4abd-981f-d0151c3a3d28\",\"ModelVersion\":1,\"Version\":\"0.1\",\"OperationType\":2306,\"Inputs\":[{\"Id\":\"MultiplyNumbersNodeViewModel : c27010c6-e5fd-4abd-981f-d0151c3a3d28\\\\nInput : A 1bd888b2-0487-4976-9ac0-d1f543a72f07\",\"DataType\":2,\"connectedOutputIdModel\":{\"Id\":\"SqrNodeViewModel : e5faaaec-f19b-4253-98d5-308b874d6d72\\\\nOutput : Result 2c0181b1-7d22-4284-a3b6-a16adb3c2cb6\",\"NodeId\":\"SqrNodeViewModel : e5faaaec-f19b-4253-98d5-308b874d6d72\"}},{\"Id\":\"MultiplyNumbersNodeViewModel : c27010c6-e5fd-4abd-981f-d0151c3a3d28\\\\nInput : B f61b8315-ba79-43c9-b600-8e5c50366b5d\",\"DataType\":2,\"connectedOutputIdModel\":{\"Id\":\"RootNodeViewModel : 891620d8-871c-4dfb-b6b6-3dea1cba575a\\nOutput : Number 7654a216-35b1-410e-b530-c48c83027910\",\"NodeId\":\"RootNodeViewModel : 891620d8-871c-4dfb-b6b6-3dea1cba575a\"}}],\"Outputs\":[{\"Id\":\"MultiplyNumbersNodeViewModel : c27010c6-e5fd-4abd-981f-d0151c3a3d28\\\\nOutput : A \\u00d7 B b5122555-3d54-4f1f-b5f3-7305e2cd5f1a\",\"DataType\":2,\"ConnectedInputsIds\":[{\"Id\":\"GreaterNodeViewModel : 3183e978-1604-4d12-a510-cc61c53bb1e0\\\\nInput : B a441eeb9-f9fe-413c-89b6-4d218a46bd9c\",\"NodeId\":\"GreaterNodeViewModel : 3183e978-1604-4d12-a510-cc61c53bb1e0\"},{\"Id\":\"ExitNodeViewModel : 4b1d6afb-5868-456e-bc0e-3144869d58a0\\nInput : Number 66a56713-f5fd-4e5a-8461-f261c6e1318a\",\"NodeId\":\"ExitNodeViewModel : 4b1d6afb-5868-456e-bc0e-3144869d58a0\"}]}],\"VisualPosition\":{\"x\":400.0,\"y\":-900.0},\"VisualCollapsed\":false,\"MechanicConnectionId\":null,\"GateDataType\":2,\"SaveData\":null},{\"Id\":\"MassEntityNodeViewModel : 3f1e9335-332a-488d-be37-aba20943a867\",\"ModelVersion\":1,\"Version\":\"0.1\",\"OperationType\":1557,\"Inputs\":[{\"Id\":\"MassEntityNodeViewModel : 3f1e9335-332a-488d-be37-aba20943a867\\\\nInput : object 7558dbb5-c337-4ee2-8b6e-ee1206349573\",\"DataType\":1,\"connectedOutputIdModel\":{\"Id\":\"SplitVectorNodeViewModel : c890160d-8dae-4aaa-9b9d-3bb10d71bd32\\\\nOutput : Y bb731f45-21ea-46ca-aa24-187a551a7b89\",\"NodeId\":\"SplitVectorNodeViewModel : c890160d-8dae-4aaa-9b9d-3bb10d71bd32\"}}],\"Outputs\":[{\"Id\":\"MassEntityNodeViewModel : 3f1e9335-332a-488d-be37-aba20943a867\\\\nOutput : Mass 3fc6b7a2-3017-4fec-b2b8-1306910a1981\",\"DataType\":2,\"ConnectedInputsIds\":[{\"Id\":\"GreaterNodeViewModel : 3183e978-1604-4d12-a510-cc61c53bb1e0\\\\nInput : A b67b72b8-4434-4033-b2dd-33f93fd3f6a9\",\"NodeId\":\"GreaterNodeViewModel : 3183e978-1604-4d12-a510-cc61c53bb1e0\"}]}],\"VisualPosition\":{\"x\":400.0,\"y\":-300.0},\"VisualCollapsed\":false,\"MechanicConnectionId\":null,\"GateDataType\":0,\"SaveData\":null},{\"Id\":\"GreaterNodeViewModel : 3183e978-1604-4d12-a510-cc61c53bb1e0\",\"ModelVersion\":1,\"Version\":\"0.1\",\"OperationType\":2820,\"Inputs\":[{\"Id\":\"GreaterNodeViewModel : 3183e978-1604-4d12-a510-cc61c53bb1e0\\\\nInput : A b67b72b8-4434-4033-b2dd-33f93fd3f6a9\",\"DataType\":2,\"connectedOutputIdModel\":{\"Id\":\"MassEntityNodeViewModel : 3f1e9335-332a-488d-be37-aba20943a867\\\\nOutput : Mass 3fc6b7a2-3017-4fec-b2b8-1306910a1981\",\"NodeId\":\"MassEntityNodeViewModel : 3f1e9335-332a-488d-be37-aba20943a867\"}},{\"Id\":\"GreaterNodeViewModel : 3183e978-1604-4d12-a510-cc61c53bb1e0\\\\nInput : B a441eeb9-f9fe-413c-89b6-4d218a46bd9c\",\"DataType\":2,\"connectedOutputIdModel\":{\"Id\":\"MultiplyNumbersNodeViewModel : c27010c6-e5fd-4abd-981f-d0151c3a3d28\\\\nOutput : A \\u00d7 B b5122555-3d54-4f1f-b5f3-7305e2cd5f1a\",\"NodeId\":\"MultiplyNumbersNodeViewModel : c27010c6-e5fd-4abd-981f-d0151c3a3d28\"}}],\"Outputs\":[{\"Id\":\"GreaterNodeViewModel : 3183e978-1604-4d12-a510-cc61c53bb1e0\\\\nOutput : Result aa5dc810-b418-4896-80f3-18faafe2e8f0\",\"DataType\":2,\"ConnectedInputsIds\":[{\"Id\":\"AndNodeViewModel : 7d8f7921-2f40-47db-98b2-360de425ae97\\\\nInput : B cc342a18-c692-412d-aa62-08f44b0d428c\",\"NodeId\":\"AndNodeViewModel : 7d8f7921-2f40-47db-98b2-360de425ae97\"}]}],\"VisualPosition\":{\"x\":1200.0,\"y\":-300.0},\"VisualCollapsed\":false,\"MechanicConnectionId\":null,\"GateDataType\":2,\"SaveData\":null},{\"Id\":\"AndNodeViewModel : 7d8f7921-2f40-47db-98b2-360de425ae97\",\"ModelVersion\":1,\"Version\":\"0.1\",\"OperationType\":2560,\"Inputs\":[{\"Id\":\"AndNodeViewModel : 7d8f7921-2f40-47db-98b2-360de425ae97\\\\nInput : A 2f0c32d8-fa40-40a3-a71a-983a51c082b0\",\"DataType\":2,\"connectedOutputIdModel\":{\"Id\":\"LessNodeViewModel : 0a1c4e0b-9b46-4a5d-80ac-1e5310698de0\\\\nOutput : Result 930f487b-8dbb-4ef4-b1d7-f1ff554d8a7f\",\"NodeId\":\"LessNodeViewModel : 0a1c4e0b-9b46-4a5d-80ac-1e5310698de0\"}},{\"Id\":\"AndNodeViewModel : 7d8f7921-2f40-47db-98b2-360de425ae97\\\\nInput : B cc342a18-c692-412d-aa62-08f44b0d428c\",\"DataType\":2,\"connectedOutputIdModel\":{\"Id\":\"GreaterNodeViewModel : 3183e978-1604-4d12-a510-cc61c53bb1e0\\\\nOutput : Result aa5dc810-b418-4896-80f3-18faafe2e8f0\",\"NodeId\":\"GreaterNodeViewModel : 3183e978-1604-4d12-a510-cc61c53bb1e0\"}}],\"Outputs\":[{\"Id\":\"AndNodeViewModel : 7d8f7921-2f40-47db-98b2-360de425ae97\\\\nOutput : Result c12b7a43-da64-41e8-8827-5168da6890c9\",\"DataType\":2,\"ConnectedInputsIds\":[{\"Id\":\"BranchNodeViewModel : 7aebd9c0-78d6-476d-8a74-d4bba7e3ca19\\\\nInput : If b66b0bda-da4b-47ac-8ae0-37e9dfd16003\",\"NodeId\":\"BranchNodeViewModel : 7aebd9c0-78d6-476d-8a74-d4bba7e3ca19\"},{\"Id\":\"ExitNodeViewModel : 85002a22-acec-4e49-a57f-29d8482ab9fb\\nInput : Number 3f519bcc-f522-45f9-9ddc-b92e2f8e972e\",\"NodeId\":\"ExitNodeViewModel : 85002a22-acec-4e49-a57f-29d8482ab9fb\"}]}],\"VisualPosition\":{\"x\":1200.0,\"y\":-900.0},\"VisualCollapsed\":false,\"MechanicConnectionId\":null,\"GateDataType\":2,\"SaveData\":null},{\"Id\":\"MultiplyNumbersNodeViewModel : 703b17ab-3071-44f3-9d61-9aee82c4594c\",\"ModelVersion\":1,\"Version\":\"0.1\",\"OperationType\":2306,\"Inputs\":[{\"Id\":\"MultiplyNumbersNodeViewModel : 703b17ab-3071-44f3-9d61-9aee82c4594c\\\\nInput : A 1c5d05d1-d5b0-45c6-b5c9-86311ccab2ec\",\"DataType\":2,\"connectedOutputIdModel\":{\"Id\":\"SplitVectorNodeViewModel : c890160d-8dae-4aaa-9b9d-3bb10d71bd32\\\\nOutput : Y bb731f45-21ea-46ca-aa24-187a551a7b89\",\"NodeId\":\"SplitVectorNodeViewModel : c890160d-8dae-4aaa-9b9d-3bb10d71bd32\"}},{\"Id\":\"MultiplyNumbersNodeViewModel : 703b17ab-3071-44f3-9d61-9aee82c4594c\\\\nInput : B 43ab7bd8-2603-4d3d-8661-cf05253064d0\",\"DataType\":2,\"connectedOutputIdModel\":{\"Id\":\"RootNodeViewModel : 891620d8-871c-4dfb-b6b6-3dea1cba575a\\nOutput : Number 7654a216-35b1-410e-b530-c48c83027910\",\"NodeId\":\"RootNodeViewModel : 891620d8-871c-4dfb-b6b6-3dea1cba575a\"}}],\"Outputs\":[{\"Id\":\"MultiplyNumbersNodeViewModel : 703b17ab-3071-44f3-9d61-9aee82c4594c\\\\nOutput : A \\u00d7 B feaa75a3-6729-47ac-93c5-6f33e5f09787\",\"DataType\":2,\"ConnectedInputsIds\":[{\"Id\":\"MultiplyNumbersNodeViewModel : 6293058c-97d1-4bb3-805e-4a90c21920a5\\\\nInput : A e128f0f4-a86a-40e0-ab06-42547c78252a\",\"NodeId\":\"MultiplyNumbersNodeViewModel : 6293058c-97d1-4bb3-805e-4a90c21920a5\"}]}],\"VisualPosition\":{\"x\":400.0,\"y\":300.0},\"VisualCollapsed\":false,\"MechanicConnectionId\":null,\"GateDataType\":2,\"SaveData\":null},{\"Id\":\"MultiplyNumbersNodeViewModel : 6293058c-97d1-4bb3-805e-4a90c21920a5\",\"ModelVersion\":1,\"Version\":\"0.1\",\"OperationType\":2306,\"Inputs\":[{\"Id\":\"MultiplyNumbersNodeViewModel : 6293058c-97d1-4bb3-805e-4a90c21920a5\\\\nInput : A e128f0f4-a86a-40e0-ab06-42547c78252a\",\"DataType\":2,\"connectedOutputIdModel\":{\"Id\":\"MultiplyNumbersNodeViewModel : 703b17ab-3071-44f3-9d61-9aee82c4594c\\\\nOutput : A \\u00d7 B feaa75a3-6729-47ac-93c5-6f33e5f09787\",\"NodeId\":\"MultiplyNumbersNodeViewModel : 703b17ab-3071-44f3-9d61-9aee82c4594c\"}},{\"Id\":\"MultiplyNumbersNodeViewModel : 6293058c-97d1-4bb3-805e-4a90c21920a5\\\\nInput : B ed0bdd86-5639-4233-8899-e3b1eaf73495\",\"DataType\":2,\"connectedOutputIdModel\":{\"Id\":\"ConstantNodeViewModel : d9886922-637a-43ae-83c3-4dab17805996\\nOutput : Number 4b50e942-d6b3-4130-af10-c8bf056568fa\",\"NodeId\":\"ConstantNodeViewModel : d9886922-637a-43ae-83c3-4dab17805996\"}}],\"Outputs\":[{\"Id\":\"MultiplyNumbersNodeViewModel : 6293058c-97d1-4bb3-805e-4a90c21920a5\\\\nOutput : A \\u00d7 B cbfdb132-c488-4951-a2d5-afb5913c9703\",\"DataType\":2,\"ConnectedInputsIds\":[{\"Id\":\"BranchNodeViewModel : 7aebd9c0-78d6-476d-8a74-d4bba7e3ca19\\\\nInput : A 86d04bfb-75bd-42be-b8fb-89156dd42230\",\"NodeId\":\"BranchNodeViewModel : 7aebd9c0-78d6-476d-8a74-d4bba7e3ca19\"}]}],\"VisualPosition\":{\"x\":1200.0,\"y\":1500.0},\"VisualCollapsed\":false,\"MechanicConnectionId\":null,\"GateDataType\":2,\"SaveData\":null},{\"Id\":\"BranchNodeViewModel : 7aebd9c0-78d6-476d-8a74-d4bba7e3ca19\",\"ModelVersion\":1,\"Version\":\"0.1\",\"OperationType\":2567,\"Inputs\":[{\"Id\":\"BranchNodeViewModel : 7aebd9c0-78d6-476d-8a74-d4bba7e3ca19\\\\nInput : If b66b0bda-da4b-47ac-8ae0-37e9dfd16003\",\"DataType\":2,\"connectedOutputIdModel\":{\"Id\":\"AndNodeViewModel : 7d8f7921-2f40-47db-98b2-360de425ae97\\\\nOutput : Result c12b7a43-da64-41e8-8827-5168da6890c9\",\"NodeId\":\"AndNodeViewModel : 7d8f7921-2f40-47db-98b2-360de425ae97\"}},{\"Id\":\"BranchNodeViewModel : 7aebd9c0-78d6-476d-8a74-d4bba7e3ca19\\\\nInput : A 86d04bfb-75bd-42be-b8fb-89156dd42230\",\"DataType\":2,\"connectedOutputIdModel\":{\"Id\":\"MultiplyNumbersNodeViewModel : 6293058c-97d1-4bb3-805e-4a90c21920a5\\\\nOutput : A \\u00d7 B cbfdb132-c488-4951-a2d5-afb5913c9703\",\"NodeId\":\"MultiplyNumbersNodeViewModel : 6293058c-97d1-4bb3-805e-4a90c21920a5\"}},{\"Id\":\"BranchNodeViewModel : 7aebd9c0-78d6-476d-8a74-d4bba7e3ca19\\\\nInput : B 028958d4-89ad-48b2-8847-48fe1d082e25\",\"DataType\":2,\"connectedOutputIdModel\":{\"Id\":\"ConstantNodeViewModel : 28e12460-6452-4107-9829-5506c734b905\\nOutput : Number 3de9685f-3f27-40ad-a39e-50bb7fed3065\",\"NodeId\":\"ConstantNodeViewModel : 28e12460-6452-4107-9829-5506c734b905\"}}],\"Outputs\":[{\"Id\":\"BranchNodeViewModel : 7aebd9c0-78d6-476d-8a74-d4bba7e3ca19\\\\nOutput : Result c241fc74-7439-4c18-84fc-9602d5434f7a\",\"DataType\":2,\"ConnectedInputsIds\":[{\"Id\":\"AddNumbersNodeViewModel : 90a3f2a8-dab3-47d3-a7f0-60c2943bd21d\\\\nInput : B 762cf95b-7e85-4134-b11c-ad8222303cec\",\"NodeId\":\"AddNumbersNodeViewModel : 90a3f2a8-dab3-47d3-a7f0-60c2943bd21d\"},{\"Id\":\"ExitNodeViewModel : 5f017648-2f8c-4dc3-a04b-31c921b2300a\\nInput : Number 17b7506e-85b7-4236-b2c3-75fff5d35214\",\"NodeId\":\"ExitNodeViewModel : 5f017648-2f8c-4dc3-a04b-31c921b2300a\"}]}],\"VisualPosition\":{\"x\":400.0,\"y\":-1500.0},\"VisualCollapsed\":false,\"MechanicConnectionId\":null,\"GateDataType\":2,\"SaveData\":null},{\"Id\":\"AddNumbersNodeViewModel : 90a3f2a8-dab3-47d3-a7f0-60c2943bd21d\",\"ModelVersion\":1,\"Version\":\"0.1\",\"OperationType\":2304,\"Inputs\":[{\"Id\":\"AddNumbersNodeViewModel : 90a3f2a8-dab3-47d3-a7f0-60c2943bd21d\\\\nInput : A 446fe98c-a8ca-4b71-a694-ff8c5e076456\",\"DataType\":2,\"connectedOutputIdModel\":{\"Id\":\"AddNumbersNodeViewModel : 0e84f0dd-56d7-4c3a-972b-3d8a91eb5ce5\\\\nOutput : A + B f042fc1d-2bef-44d0-8792-f74fc2305018\",\"NodeId\":\"AddNumbersNodeViewModel : 0e84f0dd-56d7-4c3a-972b-3d8a91eb5ce5\"}},{\"Id\":\"AddNumbersNodeViewModel : 90a3f2a8-dab3-47d3-a7f0-60c2943bd21d\\\\nInput : B 762cf95b-7e85-4134-b11c-ad8222303cec\",\"DataType\":2,\"connectedOutputIdModel\":{\"Id\":\"BranchNodeViewModel : 7aebd9c0-78d6-476d-8a74-d4bba7e3ca19\\\\nOutput : Result c241fc74-7439-4c18-84fc-9602d5434f7a\",\"NodeId\":\"BranchNodeViewModel : 7aebd9c0-78d6-476d-8a74-d4bba7e3ca19\"}}],\"Outputs\":[{\"Id\":\"AddNumbersNodeViewModel : 90a3f2a8-dab3-47d3-a7f0-60c2943bd21d\\\\nOutput : A + B 7a237a34-4aa9-4749-90fb-1ac7ebb45dcb\",\"DataType\":2,\"ConnectedInputsIds\":[{\"Id\":\"CombineVectorNodeViewModel : 5b12f256-c962-4392-86eb-abed1b7bcb43\\\\nInput : Y ef1121a8-9784-4809-9360-633e80406ab5\",\"NodeId\":\"CombineVectorNodeViewModel : 5b12f256-c962-4392-86eb-abed1b7bcb43\"}]}],\"VisualPosition\":{\"x\":1200.0,\"y\":-1500.0},\"VisualCollapsed\":false,\"MechanicConnectionId\":null,\"GateDataType\":2,\"SaveData\":null},{\"Id\":\"CombineVectorNodeViewModel : 5b12f256-c962-4392-86eb-abed1b7bcb43\",\"ModelVersion\":1,\"Version\":\"0.1\",\"OperationType\":1281,\"Inputs\":[{\"Id\":\"CombineVectorNodeViewModel : 5b12f256-c962-4392-86eb-abed1b7bcb43\\\\nInput : X b10ed6c8-c373-418f-8401-2c6a38627cdb\",\"DataType\":2,\"connectedOutputIdModel\":{\"Id\":\"ConstantNodeViewModel : 28e12460-6452-4107-9829-5506c734b905\\nOutput : Number 3de9685f-3f27-40ad-a39e-50bb7fed3065\",\"NodeId\":\"ConstantNodeViewModel : 28e12460-6452-4107-9829-5506c734b905\"}},{\"Id\":\"CombineVectorNodeViewModel : 5b12f256-c962-4392-86eb-abed1b7bcb43\\\\nInput : Y ef1121a8-9784-4809-9360-633e80406ab5\",\"DataType\":2,\"connectedOutputIdModel\":{\"Id\":\"AddNumbersNodeViewModel : 90a3f2a8-dab3-47d3-a7f0-60c2943bd21d\\\\nOutput : A + B 7a237a34-4aa9-4749-90fb-1ac7ebb45dcb\",\"NodeId\":\"AddNumbersNodeViewModel : 90a3f2a8-dab3-47d3-a7f0-60c2943bd21d\"}},{\"Id\":\"CombineVectorNodeViewModel : 5b12f256-c962-4392-86eb-abed1b7bcb43\\\\nInput : Z 333cfa55-1678-4dba-a553-e17b889fc479\",\"DataType\":2,\"connectedOutputIdModel\":{\"Id\":\"ConstantNodeViewModel : 28e12460-6452-4107-9829-5506c734b905\\nOutput : Number 3de9685f-3f27-40ad-a39e-50bb7fed3065\",\"NodeId\":\"ConstantNodeViewModel : 28e12460-6452-4107-9829-5506c734b905\"}},{\"Id\":\"CombineVectorNodeViewModel : 5b12f256-c962-4392-86eb-abed1b7bcb43\\\\nInput : W 18c88ab5-ec8c-42b6-b222-21b0e75441f8\",\"DataType\":2,\"connectedOutputIdModel\":{\"Id\":\"ConstantNodeViewModel : 28e12460-6452-4107-9829-5506c734b905\\nOutput : Number 3de9685f-3f27-40ad-a39e-50bb7fed3065\",\"NodeId\":\"ConstantNodeViewModel : 28e12460-6452-4107-9829-5506c734b905\"}}],\"Outputs\":[{\"Id\":\"CombineVectorNodeViewModel : 5b12f256-c962-4392-86eb-abed1b7bcb43\\\\nOutput : Result 8fb5ecc5-c270-4642-ad5c-b5b57a9a91c8\",\"DataType\":8,\"ConnectedInputsIds\":[{\"Id\":\"ExitNodeViewModel : 3b1841a0-432d-4e7f-8904-89d13a1a1e02\\nInput : Number 4bd88dbb-33f3-45c0-aa9f-4c6e6c91325d\",\"NodeId\":\"ExitNodeViewModel : 3b1841a0-432d-4e7f-8904-89d13a1a1e02\"}]}],\"VisualPosition\":{\"x\":2000.0,\"y\":-2100.0},\"VisualCollapsed\":false,\"MechanicConnectionId\":null,\"GateDataType\":8,\"SaveData\":null},{\"Id\":\"ExitNodeViewModel : 3b1841a0-432d-4e7f-8904-89d13a1a1e02\",\"OperationType\":512,\"Inputs\":[{\"Id\":\"ExitNodeViewModel : 3b1841a0-432d-4e7f-8904-89d13a1a1e02\\nInput : Number 4bd88dbb-33f3-45c0-aa9f-4c6e6c91325d\",\"DataType\":8,\"connectedOutputIdModel\":{\"Id\":\"CombineVectorNodeViewModel : 5b12f256-c962-4392-86eb-abed1b7bcb43\\\\nOutput : Result 8fb5ecc5-c270-4642-ad5c-b5b57a9a91c8\",\"NodeId\":\"CombineVectorNodeViewModel : 5b12f256-c962-4392-86eb-abed1b7bcb43\"}}],\"Outputs\":[],\"MechanicConnectionId\":\"force_8af7\",\"GateDataType\":8,\"SaveData\":null,\"VisualPosition\":{\"x\":2800.0,\"y\":-2100.0},\"VisualCollapsed\":false,\"ModelVersion\":1,\"Version\":\"0.1\"},{\"Id\":\"ExitNodeViewModel : 85002a22-acec-4e49-a57f-29d8482ab9fb\",\"OperationType\":512,\"Inputs\":[{\"Id\":\"ExitNodeViewModel : 85002a22-acec-4e49-a57f-29d8482ab9fb\\nInput : Number 3f519bcc-f522-45f9-9ddc-b92e2f8e972e\",\"DataType\":2,\"connectedOutputIdModel\":{\"Id\":\"AndNodeViewModel : 7d8f7921-2f40-47db-98b2-360de425ae97\\\\nOutput : Result c12b7a43-da64-41e8-8827-5168da6890c9\",\"NodeId\":\"AndNodeViewModel : 7d8f7921-2f40-47db-98b2-360de425ae97\"}}],\"Outputs\":[],\"MechanicConnectionId\":\"debugisbraking_ddd9\",\"GateDataType\":2,\"SaveData\":null,\"VisualPosition\":{\"x\":2800.0,\"y\":900.0},\"VisualCollapsed\":false,\"ModelVersion\":1,\"Version\":\"0.1\"},{\"Id\":\"ExitNodeViewModel : 4b1d6afb-5868-456e-bc0e-3144869d58a0\",\"OperationType\":512,\"Inputs\":[{\"Id\":\"ExitNodeViewModel : 4b1d6afb-5868-456e-bc0e-3144869d58a0\\nInput : Number 66a56713-f5fd-4e5a-8461-f261c6e1318a\",\"DataType\":2,\"connectedOutputIdModel\":{\"Id\":\"MultiplyNumbersNodeViewModel : c27010c6-e5fd-4abd-981f-d0151c3a3d28\\\\nOutput : A \\u00d7 B b5122555-3d54-4f1f-b5f3-7305e2cd5f1a\",\"NodeId\":\"MultiplyNumbersNodeViewModel : c27010c6-e5fd-4abd-981f-d0151c3a3d28\"}}],\"Outputs\":[],\"MechanicConnectionId\":\"debugmaxspeed_9de3\",\"GateDataType\":2,\"SaveData\":null,\"VisualPosition\":{\"x\":2800.0,\"y\":300.0},\"VisualCollapsed\":false,\"ModelVersion\":1,\"Version\":\"0.1\"},{\"Id\":\"ExitNodeViewModel : 5f017648-2f8c-4dc3-a04b-31c921b2300a\",\"OperationType\":512,\"Inputs\":[{\"Id\":\"ExitNodeViewModel : 5f017648-2f8c-4dc3-a04b-31c921b2300a\\nInput : Number 17b7506e-85b7-4236-b2c3-75fff5d35214\",\"DataType\":2,\"connectedOutputIdModel\":{\"Id\":\"BranchNodeViewModel : 7aebd9c0-78d6-476d-8a74-d4bba7e3ca19\\\\nOutput : Result c241fc74-7439-4c18-84fc-9602d5434f7a\",\"NodeId\":\"BranchNodeViewModel : 7aebd9c0-78d6-476d-8a74-d4bba7e3ca19\"}}],\"Outputs\":[],\"MechanicConnectionId\":\"debugbrakeforce_28b7\",\"GateDataType\":2,\"SaveData\":null,\"VisualPosition\":{\"x\":2800.0,\"y\":-300.0},\"VisualCollapsed\":false,\"ModelVersion\":1,\"Version\":\"0.1\"}]}","intValue":0,"floatValue":0.0,"vector2Value":{"x":0.0,"y":0.0},"vector3Value":{"x":0.0,"y":0.0,"z":0.0},"vector4Value":{"x":0.0,"y":0.0,"z":0.0,"w":0.0,"magnitude":0.0,"sqrMagnitude":0.0}},{"key":"chip_editor_position","boolValue":false,"stringValue":null,"intValue":0,"floatValue":0.0,"vector2Value":{"x":-138.912781,"y":-276.419647},"vector3Value":{"x":0.0,"y":0.0,"z":0.0},"vector4Value":{"x":0.0,"y":0.0,"z":0.0,"w":0.0,"magnitude":0.0,"sqrMagnitude":0.0}},{"key":"chip_editor_zoom","boolValue":false,"stringValue":null,"intValue":0,"floatValue":0.0,"vector2Value":{"x":0.0,"y":0.0},"vector3Value":{"x":0.496272445,"y":0.496272445,"z":0.0},"vector4Value":{"x":0.0,"y":0.0,"z":0.0,"w":0.0,"magnitude":0.0,"sqrMagnitude":0.0}}]},"saveObjectChildren":[]}],"averagePosition":{"x":3.43957,"y":0.127520934,"z":-0.0190000013}}